Workbook
Name AXPMKT: #REF!
Name backuptotal: #REF!
Name BACMKT: #REF!
Name DGMKT: #REF!
Name DIAMKT: #REF!
Name FTNTMKT: #REF!
Name GOOGLMKT: #REF!
Name GSMKT: #REF!
Name KVUEMKT: #REF!
Name LTCMKT: #REF!
Name OMKT: #REF!
Name PAYCMKT: #REF!
Name PMKTVALUE: #REF!
Name QCOMMKT: #REF!
Name totalexp: #REF!
Name VOOMKT: #REF!
Name VZMKT: #REF!
Name WBAMKT: #REF!

Sheet Raw Data, Screening
A1: Company | B1: Revenue (CAGR) | C1: EBITDA Margin | D1: ROE | E1: ROIC | F1: Debt-to-EBITDA | G1: EPS σ | H1: EV-to-EBITDA | I1: Industry | U1: Screening Score | V1: Column1 | W1: 2025
A2: Chevron | B2: =[1]Notes!$D$7 -> 0.037067093 | C2: =[1]Notes!$D$8 -> 0.21738233 | D2: =[1]Notes!$D$9 -> 0.063998626 | E2: =[1]Notes!$D$10 -> 0.067607237 | F2: =[1]Notes!$D$11 -> 0.9918719 | G2: =[1]Notes!$D$12 -> 6.8587428 | H2: =[1]Notes!$D$13 -> 7.158389 | I2: =[1]Notes!$D$14 -> Oil & Gas Integrated | U2: Revenue (CAGR) | W2: =(([1]Statements!AB21/[1]Statements!V21)^(1/7))-1 -> -1
A3: Bank of America | B3: =[2]Notes!$D$7 -> 0.031147913 | C3: =[2]Notes!$D$8 -> 0.34997392 | D3: =[2]Notes!$D$9 -> 0.095814248 | E3: =[2]Notes!$D$10 -> 0.011570559 | F3: =[2]Notes!$D$11 -> 9.7069638 | G3: =[2]Notes!$D$12 -> 0.62268042 | H3: =[2]Notes!$D$13 -> 5.7999968 | I3: =[2]Notes!$D$14 -> Banks, Diversified | U3: EBITDA Margin | W3: =[1]Statements!AB44/[1]Statements!AB21 -> #DIV/0!
A4: AMD | B4: =[3]Notes!$D$7 -> 0.2636908 | C4: =[3]Notes!$D$8 -> 0.14194983 | D4: =[3]Notes!$D$9 -> 0.06776298 | E4: =[3]Notes!$D$10 -> 0.017265524 | F4: =[3]Notes!$D$11 -> 0.65527761 | G4: =[3]Notes!$D$12 -> 0.9787008 | H4: =[3]Notes!$D$13 -> 77.274818 | I4: =[3]Notes!$D$14 -> Semiconductors | U4: ROE | W4: =[1]Statements!AB38/[1]Statements!AN39 -> #DIV/0!
A5: Amazon | B5: =[4]Notes!$D$6 -> 0.14344471 | C5: =[4]Notes!$D$7 -> 0.11155297 | D5: =[4]Notes!$D$8 -> 0.18894822 | E5: =[4]Notes!$D$9 -> 0.041244089 | F5: =[4]Notes!$D$10 -> 0.82085652 | G5: =[4]Notes!$D$11 -> 2.5375167 | H5: =[4]Notes!$D$12 -> 31.678901 | I5: =[4]Notes!$D$13 -> Internet Retail | U5: ROIC | W5: =([1]Statements!AB34+[1]Statements!AB30)*(1-([1]Statements!AB35/[1]Statements!AB34))/([1]Statements!AN14-[1]Statements!AN32+[1]Statements!AN19) -> #DIV/0!
A6: Applied Materials | B6: =[5]!Table810[[#This Row],[2025]] -> 0.099453462 | C6: =[5]Notes!$D$7 -> 0.29219543 | D6: =[5]Notes!$D$8 -> 0.34278717 | E6: =[5]Notes!$D$9 -> 0.095864899 | F6: =[5]Notes!$D$10 -> 0.79080709 | G6: =[5]Notes!$D$11 -> 2.3251312 | H6: =[5]Notes!$D$12 -> 31.09786 | I6: =[5]Notes!$D$13 -> Semiconductor Equipment & Materials | U6: Debt-to-EBITDA | W6: =[1]Statements!AN43/[1]Statements!AB44 -> #DIV/0!
A7: Cadence Design Systems | B7: =[6]!Table810[[#This Row],[2025]] -> 0.12404466 | C7: =[6]Notes!$D$8 -> 0.28922953 | D7: =[6]Notes!$D$9 -> 0.202567 | E7: =[6]Notes!$D$10 -> 0.064283198 | F7: =[6]Notes!$D$11 -> 1.6189064 | G7: =[6]Notes!$D$12 -> 0.74157179 | H7: =[6]Notes!$D$13 -> 53.937194 | I7: =[6]Notes!$D$14 -> Software | U7: EPS σ | W7: =_xlfn.STDEV.S([1]Statements!V41:AB41) -> 0.29812234
A8: Costco | B8: =[7]Observations!$D$7 -> 0.087804548 | C8: =[7]!Table810[[#This Row],[2025]] -> 0.037724127 | D8: =[7]Observations!$D$9 -> 0.27770539 | E8: =[7]Observations!$D$10 -> 0.23427061 | F8: =[7]Observations!$D$11 -> 0.55022633 | G8: =[7]Observations!$D$12 -> 3.6535036 | H8: =[7]Observations!$D$13 -> 39.487034 | I8: =[7]Observations!$D$14 -> Discount Stores | U8: EV-to-EBITDA | W8: =[1]Statements!AN44/[1]Statements!AB44 -> #DIV/0!
A9: Dexcom | B9: =[8]Notes!$D$5 -> 0.17856932 | C9: =[8]Notes!$D$6 -> 0.1955813 | D9: =[8]Notes!$D$7 -> 0.30455208 | E9: =[8]Notes!$D$8 -> 0.20161871 | F9: =[8]!Table810[[#This Row],[2025]] -> 1.3609344 | G9: =[8]Notes!$D$10 -> 0.61154704 | H9: =[8]Notes!$D$11 -> 31.65159 | I9: =[8]Notes!$D$12 -> Medical Devices | U9: Industry | W9: Oil & Gas Integrated
A10: Elevance Health | B10: =[9]Notes!$D$5 -> 0.096912497 | C10: =[9]Notes!$D$6 -> 0.043892028 | D10: =[9]Notes!$D$7 -> 0.12858311 | E10: =[9]Notes!$D$8 -> 0.1383875 | F10: =[9]Notes!$D$9 -> 3.6665904 | G10: =[9]!Table810[[#This Row],[2025]] -> 3.3412957 | H10: =[9]Notes!$D$11 -> 11.41099 | I10: =[9]Notes!$D$12 -> Healthcare
A11: Fortinet | B11: {=TRANSPOSE([10]!Table810[2025])} -> 0.17777133 | C11: 0.30659156 | D11: 1.497697 | E11: 0.61386983 | F11: 0.47791049 | G11: 0.77956319 | H11: 28.562957 | I11: Software
A12: Delta Airlines | B12: {=TRANSPOSE([11]!Table810[2025])} -> 0.043579938 | C12: 0.091881826 | D12: 0.24001343 | E12: 0.12021862 | F12: 2.4239093 | G12: 9.6578962 | H12: 8.3207077 | I12: Airlines
A13: FedEx | B13: {=TRANSPOSE([12]!Table810[2025])} -> 0.03375663 | C13: 0.059333985 | D13: 0.14575245 | E13: 0.073614115 | F13: 3.9446042 | G13: 6.6980748 | H13: 13.006358 | I13: Freight & Logistics
A14: Starbucks | B14: {=TRANSPOSE([13]!Table810[2025])} -> 0.049536841 | C14: 0.12428061 | D14: -0.22951975 | E14: 0.22890089 | F14: 3.4784152 | G14: 1.0618675 | H14: 34.833562 | I14: Restaurants
A15: Kratos Defense | B15: {=TRANSPOSE([14]!Table810[2025])} -> 0.094129539 | C15: 0.019008019 | D15: 0.011020388 | E15: 0.0095220492 | F15: 0 | G15: 0.28429854 | H15: 642.83797 | I15: Aerospace & Defense
A16: California Water Service Group | B16: {=TRANSPOSE([15]!Table810[2025])} -> 0.049203495 | C16: 0.37018362 | D16: 0.075572317 | E16: 0.028084799 | F16: 4.3330731 | G16: 0.79501835 | H16: 11.160364 | I16: Utilities
A17: Broadcom | B17: {=TRANSPOSE([16]!Table810[2025])} -> 0.16005944 | C17: 0.4306823 | D17: 0.28448064 | E17: 0.22867202 | F17: 2.3672906 | G17: 9.0838295 | H17: 72.568037 | I17: Semiconductors
A18: Exxon Mobil | B18: {=TRANSPOSE([17]!Table810[2025])} -> 0.032827288 | C18: 0.27982887 | D18: 0.1078627 | E18: 0.1554335 | F18: 0.3683967 | G18: 5.7462639 | H18: 6.7156586 | I18: Oil & Gas Integrated

Sheet Dashboard, Screening
B3: Row Labels | C3: Revenue (CAGR) μ | D3: EBITDA Margin μ | E3: ROEμ | F3: ROICμ | G3: D/Eμ | H3: EPS σ μ | I3: EV-to-EBITDAμ
B4: Aerospace & Defense | C4: 0.094129539 | D4: 0.019008019 | E4: 0.011020388 | F4: 0.0095220492 | G4: 0 | H4: 0.28429854 | I4: 642.83797
B5: Kratos Defense | C5: 0.094129539 | D5: 0.019008019 | E5: 0.011020388 | F5: 0.0095220492 | G5: 0 | H5: 0.28429854 | I5: 642.83797
B6: Airlines | C6: 0.043579938 | D6: 0.091881826 | E6: 0.24001343 | F6: 0.12021862 | G6: 2.4239093 | H6: 9.6578962 | I6: 8.3207077
B7: Delta Airlines | C7: 0.043579938 | D7: 0.091881826 | E7: 0.24001343 | F7: 0.12021862 | G7: 2.4239093 | H7: 9.6578962 | I7: 8.3207077
B8: Banks, Diversified | C8: 0.031147913 | D8: 0.34997392 | E8: 0.095814248 | F8: 0.011570559 | G8: 9.7069638 | H8: 0.62268042 | I8: 5.7999968
B9: Bank of America | C9: 0.031147913 | D9: 0.34997392 | E9: 0.095814248 | F9: 0.011570559 | G9: 9.7069638 | H9: 0.62268042 | I9: 5.7999968
B10: Discount Stores | C10: 0.087804548 | D10: 0.037724127 | E10: 0.27770539 | F10: 0.23427061 | G10: 0.55022633 | H10: 3.6535036 | I10: 39.487034
B11: Costco | C11: 0.087804548 | D11: 0.037724127 | E11: 0.27770539 | F11: 0.23427061 | G11: 0.55022633 | H11: 3.6535036 | I11: 39.487034
B12: Freight & Logistics | C12: 0.03375663 | D12: 0.059333985 | E12: 0.14575245 | F12: 0.073614115 | G12: 3.9446042 | H12: 6.6980748 | I12: 13.006358
B13: FedEx | C13: 0.03375663 | D13: 0.059333985 | E13: 0.14575245 | F13: 0.073614115 | G13: 3.9446042 | H13: 6.6980748 | I13: 13.006358
B14: Healthcare | C14: 0.096912497 | D14: 0.043892028 | E14: 0.12858311 | F14: 0.1383875 | G14: 3.6665904 | H14: 3.3412957 | I14: 11.41099
B15: Elevance Health | C15: 0.096912497 | D15: 0.043892028 | E15: 0.12858311 | F15: 0.1383875 | G15: 3.6665904 | H15: 3.3412957 | I15: 11.41099
... B34: Grand Total | C34: 0.10438576 | D34: 0.19259021 | E34: 0.23110845 | F34: 0.13593717 | G34: 2.3242273 | H34: 3.1269524 | I34: 68.79917

Sheet Optimization
B3: Portfolio Simulator | I3: Data Showcase
B4: Ticker | C4: Name | D4: Shares | E4: Price | F4: Mkt Value | G4: Pos Ratio | J4: R, 2017 | K4: R, 2018 | L4: R, 2019 | M4: R, 2020 | N4: R, 2021 | O4: R. 2022 | P4: R, 2023 | Q4: R, 2024 | R4: R, 2025 | S4: μ | T4: σ | U4: β
B5: VOO | C5: #VALUE! | D5: 6.374 | E5: {=_FV(C5,"Price")} -> 680.95 | F5: =D5*E5 -> 4340.3753 | G5: =F5/$F$27 -> 0.10774474 | I5: VOO | J5: ='Data & Analysis'!AC5 -> 0.25263356 | K5: ='Data & Analysis'!AD5 -> -0.0031294809 | L5: ='Data & Analysis'!AE5 -> 0.21657086 | M5: ='Data & Analysis'!AF5 -> 0.17493662 | N5: ='Data & Analysis'!AG5 -> 0.22327455 | O5: ='Data & Analysis'!AH5 -> -0.069349585 | P5: ='Data & Analysis'!AI5 -> 0.20317025 | Q5: ='Data & Analysis'!AJ5 -> 0.24575445 | R5: ='Data & Analysis'!AK5 -> 0.22730931 | S5: =AVERAGE(J5:R5) -> 0.16346339 | T5: =_xlfn.STDEV.S(J5:R5) -> 0.11665149 | U5: {=_FV('Data & Analysis'!C5,"Beta")} -> 1.0001
B6: BAC | C6: #VALUE! | D6: 76.3492 | E6: {=_FV(C6,"Price")} -> 57.875 | F6: =D6*E6 -> 4418.7099 | G6: =F6/$F$27 -> 0.10968931 | I6: DIA | J6: ='Data & Analysis'!AC6 -> 0.31990622 | K6: ='Data & Analysis'!AD6 -> 9.7742591e-05 | L6: ='Data & Analysis'!AE6 -> 0.16704114 | M6: ='Data & Analysis'!AF6 -> 0.10187341 | N6: ='Data & Analysis'!AG6 -> 0.19203014 | O6: ='Data & Analysis'!AH6 -> 0.009112192 | P6: ='Data & Analysis'!AI6 -> 0.15036946 | Q6: ='Data & Analysis'!AJ6 -> 0.18746589 | R6: ='Data & Analysis'!AK6 -> 0.18390247 | S6: =AVERAGE(J6:R6) -> 0.14575541 | T6: =_xlfn.STDEV.S(J6:R6) -> 0.098711919 | U6: {=_FV('Data & Analysis'!C6,"Beta")} -> 0.9322
B7: COST | C7: #VALUE! | D7: 3 | E7: {=_FV(C7,"Price")} -> 946.68 | F7: =D7*E7 -> 2840.04 | G7: =F7/$F$27 -> 0.070500671 | I7: TSLA | J7: ='Data & Analysis'!AC7 -> 0.34071492 | K7: ='Data & Analysis'!AD7 -> -0.14313341 | L7: ='Data & Analysis'!AE7 -> 0.75080756 | M7: ='Data & Analysis'!AF7 -> 1.8081111 | N7: ='Data & Analysis'!AG7 -> 0.16589307 | O7: ='Data & Analysis'!AH7 -> -0.58920966 | P7: ='Data & Analysis'!AI7 -> 0.078095755 | Q7: ='Data & Analysis'!AJ7 -> 0.77024071 | R7: ='Data & Analysis'!AK7 -> 0.017736 | S7: =AVERAGE(J7:R7) -> 0.35547289 | T7: =_xlfn.STDEV.S(J7:R7) -> 0.68980754 | U7: {=_FV('Data & Analysis'!C7,"Beta")} -> 1.8242 | XEC7: Current Stock Portfolio
B8: AMZN | C8: #VALUE! | D8: 12 | E8: {=_FV(C8,"Price")} -> 240.14 | F8: =D8*E8 -> 2881.68 | G8: =F8/$F$27 -> 0.071534336 | I8: BAC | J8: ='Data & Analysis'!AC8 -> 0.37630852 | K8: ='Data & Analysis'!AD8 -> -0.076390847 | L8: ='Data & Analysis'!AE8 -> 0.18782742 | M8: ='Data & Analysis'!AF8 -> -0.04856196 | N8: ='Data & Analysis'!AG8 -> 0.47975337 | O8: ='Data & Analysis'!AH8 -> -0.21369915 | P8: ='Data & Analysis'!AI8 -> 0.015947382 | Q8: ='Data & Analysis'!AJ8 -> 0.35553863 | R8: ='Data & Analysis'!AK8 -> 0.26063473 | S8: =AVERAGE(J8:R8) -> 0.14859534 | T8: =_xlfn.STDEV.S(J8:R8) -> 0.23895057 | U8: {=_FV('Data & Analysis'!C8,"Beta")} -> 1.1436 | XEC8: Ticker | XED8: Name | XEE8: Shares | XEF8: Price | XEG8: Mkt Value | XEH8: Pos Ratio
B9: O | C9: #VALUE! | D9: 30.81227 | E9: {=_FV(C9,"Price")} -> 63.025 | F9: =D9*E9 -> 1941.9433 | G9: =F9/$F$27 -> 0.048206472 | I9: SBUX | J9: ='Data & Analysis'!AC9 -> 0.068469403 | K9: ='Data & Analysis'!AD9 -> 0.22688187 | L9: ='Data & Analysis'!AE9 -> 0.25734346 | M9: ='Data & Analysis'!AF9 -> 0.17168137 | N9: ='Data & Analysis'!AG9 -> 0.052102103 | O9: ='Data & Analysis'!AH9 -> 0.14725009 | P9: ='Data & Analysis'!AI9 -> -0.11495003 | Q9: ='Data & Analysis'!AJ9 -> 0.19366658 | R9: ='Data & Analysis'!AK9 -> 0.0094611099 | S9: =AVERAGE(J9:R9) -> 0.112434 | T9: =_xlfn.STDEV.S(J9:R9) -> 0.11900523 | U9: {=_FV('Data & Analysis'!C9,"Beta")} -> 0.9479 | XEC9: VOO | XED9: #VALUE! | XEE9: 6.374 | XEF9: {=_FV(XED9,"Price")} -> 680.95 | XEG9: =XEE9*XEF9 -> 4340.3753 | XEH9: =XEG9/$XEG$33 -> 0.10776749
B10: SBUX | C10: #VALUE! | D10: 18.2754 | E10: {=_FV(C10,"Price")} -> 104.06 | F10: =D10*E10 -> 1901.7381 | G10: =F10/$F$27 -> 0.047208425 | I10: O | J10: ='Data & Analysis'!AC10 -> -0.0033746044 | K10: ='Data & Analysis'!AD10 -> 0.35510338 | L10: ='Data & Analysis'!AE10 -> 0.21499874 | M10: ='Data & Analysis'!AF10 -> -0.17896252 | N10: ='Data & Analysis'!AG10 -> 0.2826536 | O10: ='Data & Analysis'!AH10 -> 0.071207577 | P10: ='Data & Analysis'!AI10 -> -0.10759247 | Q10: ='Data & Analysis'!AJ10 -> 0.11423381 | R10: ='Data & Analysis'!AK10 -> 0.24007396 | S10: =AVERAGE(J10:R10) -> 0.10981572 | T10: =_xlfn.STDEV.S(J10:R10) -> 0.18133222 | U10: {=_FV('Data & Analysis'!C10,"Beta")} -> 0.7105 | XEC10: BAC | XED10: #VALUE! | XEE10: 76.3492 | XEF10: {=_FV(XED10,"Price")} -> 57.875 | XEG10: =XEE10*XEF10 -> 4418.7099 | XEH10: =XEG10/$XEG$33 -> 0.10971247
B11: DIA | C11: #VALUE! | D11: 4.787 | E11: {=_FV(C11,"Price")} -> 521.71 | F11: =D11*E11 -> 2497.4258 | G11: =F11/$F$27 -> 0.061995674 | I11: VZ | J11: ='Data & Analysis'!AC11 -> 0.20947157 | K11: ='Data & Analysis'!AD11 -> 0.1260411 | L11: ='Data & Analysis'!AE11 -> 0.17388834 | M11: ='Data & Analysis'!AF11 -> 0.019774755 | N11: ='Data & Analysis'!AG11 -> 0.075536227 | O11: ='Data & Analysis'!AH11 -> -0.12091901 | P11: ='Data & Analysis'!AI11 -> 0.15773565 | Q11: ='Data & Analysis'!AJ11 -> 0.06191901 | R11: ='Data & Analysis'!AK11 -> 0.23916904 | S11: =AVERAGE(J11:R11) -> 0.10473519 | T11: =_xlfn.STDEV.S(J11:R11) -> 0.11062957 | U11: {=_FV('Data & Analysis'!C11,"Beta")} -> 0.2253 | XEC11: COST | XED11: #VALUE! | XEE11: 3 | XEF11: {=_FV(XED11,"Price")} -> 946.68 | XEG11: =XEE11*XEF11 -> 2840.04 | XEH11: =XEG11/$XEG$33 -> 0.070515558
B12: VZ | C12: #VALUE! | D12: 50.42404 | E12: {=_FV(C12,"Price")} -> 44.08 | F12: =D12*E12 -> 2222.6917 | G12: =F12/$F$27 -> 0.055175721 | I12: AMZN | J12: ='Data & Analysis'!AC12 -> 0.5664283 | K12: ='Data & Analysis'!AD12 -> 0.16951124 | L12: ='Data & Analysis'!AE12 -> 0.15591116 | M12: ='Data & Analysis'!AF12 -> 0.46754891 | N12: ='Data & Analysis'!AG12 -> -0.06934493 | O12: ='Data & Analysis'!AH12 -> -0.37177418 | P12: ='Data & Analysis'!AI12 -> 0.40872428 | Q12: ='Data & Analysis'!AJ12 -> 0.42621062 | R12: ='Data & Analysis'!AK12 -> 0.010296855 | S12: =AVERAGE(J12:R12) -> 0.19594581 | T12: =_xlfn.STDEV.S(J12:R12) -> 0.30388615 | U12: {=_FV('Data & Analysis'!C12,"Beta")} -> 1.4742 | XEC12: V | XED12: #VALUE! | XEE12: 8 | XEF12: {=_FV(XED12,"Price")} -> 341.59 | XEG12: =XEE12*XEF12 -> 2732.72 | XEH12: =XEG12/$XEG$33 -> 0.067850902
B13: V | C13: #VALUE! | D13: 8 | E13: {=_FV(C13,"Price")} -> 341.59 | F13: =D13*E13 -> 2732.72 | G13: =F13/$F$27 -> 0.067836578 | I13: GOOGL | J13: ='Data & Analysis'!AC13 -> 0.36564515 | K13: ='Data & Analysis'!AD13 -> -0.048866815 | L13: ='Data & Analysis'!AE13 -> 0.24104707 | M13: ='Data & Analysis'!AF13 -> 0.24320795 | N13: ='Data & Analysis'!AG13 -> 0.39267333 | O13: ='Data & Analysis'!AH13 -> -0.31407281 | P13: ='Data & Analysis'!AI13 -> 0.34888182 | Q13: ='Data & Analysis'!AJ13 -> 0.38244328 | R13: ='Data & Analysis'!AK13 -> 0.55502507 | S13: =AVERAGE(J13:R13) -> 0.24066489 | T13: =_xlfn.STDEV.S(J13:R13) -> 0.26479476 | U13: {=_FV('Data & Analysis'!C13,"Beta")} -> 1.2646 | XEC13: AMZN | XED13: #VALUE! | XEE13: 12 | XEF13: {=_FV(XED13,"Price")} -> 240.14 | XEG13: =XEE13*XEF13 -> 2881.68 | XEH13: =XEG13/$XEG$33 -> 0.071549441
B14: TSLA | C14: #VALUE! | D14: 2 | E14: {=_FV(C14,"Price")} -> 411.84 | F14: =D14*E14 -> 823.68 | G14: =F14/$F$27 -> 0.020446893 | I14: CRM | J14: ='Data & Analysis'!AC14 -> 0.36461473 | K14: ='Data & Analysis'!AD14 -> 0.28832505 | L14: ='Data & Analysis'!AE14 -> 0.18200012 | M14: ='Data & Analysis'!AF14 -> 0.21288099 | N14: ='Data & Analysis'!AG14 -> 0.030878903 | O14: ='Data & Analysis'!AH14 -> -0.32567972 | P14: ='Data & Analysis'!AI14 -> 0.51488428 | Q14: ='Data & Analysis'!AJ14 -> 0.20553179 | R14: ='Data & Analysis'!AK14 -> -0.75655115 | S14: =AVERAGE(J14:R14) -> 0.079653887 | T14: =_xlfn.STDEV.S(J14:R14) -> 0.39117683 | U14: {=_FV('Data & Analysis'!C14,"Beta")} -> 1.1916 | XEC14: O | XED14: #VALUE! | XEE14: 43.81227 | XEF14: {=_FV(XED14,"Price")} -> 63.025 | XEG14: =XEE14*XEF14 -> 2761.2683 | XEH14: =XEG14/$XEG$33 -> 0.06855973
B15: CRM | C15: #VALUE! | D15: 6 | E15: {=_FV(C15,"Price")} -> 157.97 | F15: =D15*E15 -> 947.82 | G15: =F15/$F$27 -> 0.023528523 | I15: CVX | J15: ='Data & Analysis'!AC15 -> 0.20442238 | K15: ='Data & Analysis'!AD15 -> -0.00011143924 | L15: ='Data & Analysis'!AE15 -> 0.027877579 | M15: ='Data & Analysis'!AF15 -> -0.10254983 | N15: ='Data & Analysis'!AG15 -> 0.52968203 | O15: ='Data & Analysis'!AH15 -> 0.35283573 | P15: ='Data & Analysis'!AI15 -> -0.084009611 | Q15: ='Data & Analysis'!AJ15 -> 0.098241008 | R15: ='Data & Analysis'!AK15 -> 0.19563423 | S15: =AVERAGE(J15:R15) -> 0.13578023 | T15: =_xlfn.STDEV.S(J15:R15) -> 0.20832471 | U15: {=_FV('Data & Analysis'!C15,"Beta")} -> 0.4901 | XEC15: DIA | XED15: #VALUE! | XEE15: 4.787 | XEF15: {=_FV(XED15,"Price")} -> 521.71 | XEG15: =XEE15*XEF15 -> 2497.4258 | XEH15: =XEG15/$XEG$33 -> 0.062008765
B16: CVX | C16: #VALUE! | D16: 9.22635 | E16: {=_FV(C16,"Price")} -> 168.43 | F16: =D16*E16 -> 1553.9941 | G16: =F16/$F$27 -> 0.038576087 | I16: AMD | J16: ='Data & Analysis'!AC16 -> 0.28139426 | K16: ='Data & Analysis'!AD16 -> 0.5746816 | L16: ='Data & Analysis'!AE16 -> 0.65515472 | M16: ='Data & Analysis'!AF16 -> 0.60000486 | N16: ='Data & Analysis'!AG16 -> 0.28823657 | O16: ='Data & Analysis'!AH16 -> -0.41890291 | P16: ='Data & Analysis'!AI16 -> 0.80263092 | Q16: ='Data & Analysis'!AJ16 -> -0.36895797 | R16: ='Data & Analysis'!AK16 -> 1.5374652 | S16: =AVERAGE(J16:R16) -> 0.43907858 | T16: =_xlfn.STDEV.S(J16:R16) -> 0.59856816 | U16: {=_FV('Data & Analysis'!C16,"Beta")} -> 2.4703 | XEC16: VZ | XED16: #VALUE! | XEE16: 50.42404 | XEF16: {=_FV(XED16,"Price")} -> 44.08 | XEG16: =XEE16*XEF16 -> 2222.6917 | XEH16: =XEG16/$XEG$33 -> 0.055187372
B17: AMD | C17: #VALUE! | D17: 5 | E17: {=_FV(C17,"Price")} -> 539.49 | F17: =D17*E17 -> 2697.45 | G17: =F17/$F$27 -> 0.066961041 | I17: LULU | J17: ='Data & Analysis'!AC17 -> 0.14712178 | K17: ='Data & Analysis'!AD17 -> 0.63653015 | L17: ='Data & Analysis'!AE17 -> 0.48216636 | M17: ='Data & Analysis'!AF17 -> 0.31699061 | N17: ='Data & Analysis'!AG17 -> 0.015337539 | O17: ='Data & Analysis'!AH17 -> -0.08396538 | P17: ='Data & Analysis'!AI17 -> 0.39124385 | Q17: ='Data & Analysis'!AJ17 -> -0.091351695 | R17: ='Data & Analysis'!AK17 -> -1.2876099 | S17: =AVERAGE(J17:R17) -> 0.058495927 | T17: =_xlfn.STDEV.S(J17:R17) -> 0.56520222 | U17: {=_FV('Data & Analysis'!C17,"Beta")} -> 0.8798 | XEC17: SBUX | XED17: #VALUE! | XEE17: 18.2754 | XEF17: {=_FV(XED17,"Price")} -> 104.06 | XEG17: =XEE17*XEF17 -> 1901.7381 | XEH17: =XEG17/$XEG$33 -> 0.047218393
B18: LULU | C18: #VALUE! | D18: 7 | E18: {=_FV(C18,"Price")} -> 114.29 | F18: =D18*E18 -> 800.03 | G18: =F18/$F$27 -> 0.019859809 | I18: LMT | J18: ='Data & Analysis'!AC18 -> 0.39590723 | K18: ='Data & Analysis'!AD18 -> -0.14416424 | L18: ='Data & Analysis'!AE18 -> 0.4403192 | M18: ='Data & Analysis'!AF18 -> -0.22595726 | N18: ='Data & Analysis'!AG18 -> 0.24940204 | O18: ='Data & Analysis'!AH18 -> 0.22644398 | P18: ='Data & Analysis'!AI18 -> -0.019885852 | Q18: ='Data & Analysis'!AJ18 -> 0.12880175 | R18: ='Data & Analysis'!AK18 -> 0.12960543 | S18: =AVERAGE(J18:R18) -> 0.13116359 | T18: =_xlfn.STDEV.S(J18:R18) -> 0.22773058 | U18: {=_FV('Data & Analysis'!C18,"Beta")} -> 0.1212 | XEC18: CRM | XED18: #VALUE! | XEE18: 6 | XEF18: {=_FV(XED18,"Price")} -> 157.97 | XEG18: =XEE18*XEF18 -> 947.82 | XEH18: =XEG18/$XEG$33 -> 0.023533491
B19: GOOGL | C19: #VALUE! | D19: 4.57222 | E19: {=_FV(C19,"Price")} -> 353.65 | F19: =D19*E19 -> 1616.9656 | G19: =F19/$F$27 -> 0.04013928 | I19: UPS | J19: ='Data & Analysis'!AC19 -> 0.21877248 | K19: ='Data & Analysis'!AD19 -> -0.11318196 | L19: ='Data & Analysis'!AE19 -> 0.060653471 | M19: ='Data & Analysis'!AF19 -> 0.46855365 | N19: ='Data & Analysis'!AG19 -> 0.31079914 | O19: ='Data & Analysis'!AH19 -> -0.018299312 | P19: ='Data & Analysis'!AI19 -> -0.17837337 | Q19: ='Data & Analysis'!AJ19 -> -0.1116137 | R19: ='Data & Analysis'!AK19 -> 0.056620972 | S19: =AVERAGE(J19:R19) -> 0.077103487 | T19: =_xlfn.STDEV.S(J19:R19) -> 0.2164486 | U19: {=_FV('Data & Analysis'!C19,"Beta")} -> 1.0164 | XEC19: CVX | XED19: #VALUE! | XEE19: 9.22635 | XEF19: {=_FV(XED19,"Price")} -> 168.43 | XEG19: =XEE19*XEF19 -> 1553.9941 | XEH19: =XEG19/$XEG$33 -> 0.038584232
B20: LMT | C20: #VALUE! | D20: 2.0881 | E20: {=_FV(C20,"Price")} -> 502.09 | F20: =D20*E20 -> 1048.4141 | G20: =F20/$F$27 -> 0.026025655 | I20: XOM | J20: ='Data & Analysis'!AC20 -> 0.12596392 | K20: ='Data & Analysis'!AD20 -> -0.075658468 | L20: ='Data & Analysis'!AE20 -> -0.048546703 | M20: ='Data & Analysis'!AF20 -> -0.1591883 | N20: ='Data & Analysis'!AG20 -> 0.63795981 | O20: ='Data & Analysis'!AH20 -> 0.49536374 | P20: ='Data & Analysis'!AI20 -> -0.049823384 | Q20: ='Data & Analysis'!AJ20 -> 0.10815792 | R20: ='Data & Analysis'!AK20 -> 0.29773109 | S20: =AVERAGE(J20:R20) -> 0.14799551 | T20: =_xlfn.STDEV.S(J20:R20) -> 0.27553743 | U20: {=_FV('Data & Analysis'!C20,"Beta")} -> 0.1723 | XEC20: XOM | XED20: #VALUE! | XEE20: 10.9633 | XEF20: {=_FV(XED20,"Price")} -> 136.04 | XEG20: =XEE20*XEF20 -> 1491.4473 | XEH20: =XEG20/$XEG$33 -> 0.037031253
... B24: SO | C24: #VALUE! | D24: 11.0205 | E24: {=_FV(C24,"Price")} -> 96.75 | F24: =D24*E24 -> 1066.2334 | G24: =F24/$F$27 -> 0.026467996 | I24: DUK | J24: ='Data & Analysis'!AC24 -> 0.10045711 | K24: ='Data & Analysis'!AD24 -> 0.21050135 | L24: ='Data & Analysis'!AE24 -> 0.19606773 | M24: ='Data & Analysis'!AF24 -> 0.052736296 | N24: ='Data & Analysis'!AG24 -> 0.19234302 | O24: ='Data & Analysis'!AH24 -> 0.055722029 | P24: ='Data & Analysis'!AI24 -> 0.020597051 | Q24: ='Data & Analysis'!AJ24 -> 0.23311266 | R24: ='Data & Analysis'!AK24 -> 0.19547871 | S24: =AVERAGE(J24:R24) -> 0.13966844 | T24: =_xlfn.STDEV.S(J24:R24) -> 0.081500862 | U24: {=_FV('Data & Analysis'!C24,"Beta")} -> 0.361 | XEC24: GOOGL | XED24: #VALUE! | XEE24: 4.57222 | XEF24: {=_FV(XED24,"Price")} -> 353.65 | XEG24: =XEE24*XEF24 -> 1616.9656 | XEH24: =XEG24/$XEG$33 -> 0.040147756
B25: n/a | C25: n/a | D25: n/a | E25: n/a | F25: n/a | G25: 0 | XEC25: LMT | XED25: #VALUE! | XEE25: 2.0881 | XEF25: {=_FV(XED25,"Price")} -> 502.09 | XEG25: =XEE25*XEF25 -> 1048.4141 | XEH25: =XEG25/$XEG$33 -> 0.02603115
B26: n/a | C26: n/a | D26: n/a | E26: n/a | F26: n/a | G26: 0 | XEC26: SO | XED26: #VALUE! | XEE26: 9.2205 | XEF26: {=_FV(XED26,"Price")} -> 96.75 | XEG26: =XEE26*XEF26 -> 892.08337 | XEH26: =XEG26/$XEG$33 -> 0.022149602
E27: Total | F27: =SUM(F5:F24) -> 40283.872 | G27: =SUM(G5:G24) -> 1 | XEC27: UPS | XED27: #VALUE! | XEE27: 8.13097 | XEF27: {=_FV(XED27,"Price")} -> 107.98 | XEG27: =XEE27*XEF27 -> 877.98214 | XEH27: =XEG27/$XEG$33 -> 0.021799482
E28: Current P | F28: =XEG31 -> 40275.367 | XEC28: DUK | XED28: #VALUE! | XEE28: 4.47715 | XEF28: {=_FV(XED28,"Price")} -> 128.31 | XEG28: =XEE28*XEF28 -> 574.46312 | XEH28: =XEG28/$XEG$33 -> 0.014263386
E29: Deficit/Surp | F29: =F28-F27 -> -8.5044055 | XEC29: n/a | XED29: n/a | XEE29: n/a | XEF29: n/a | XEG29: n/a | XEH29: 0
XEC30: n/a | XED30: n/a | XEE30: n/a | XEF30: n/a | XEG30: n/a | XEH30: 0
B31: Portfolio Consensus | I31: Portfolio Optimization Simulation | XEF31: Total | XEG31: =SUM(XEG9:XEG28) -> 40275.367 | XEH31: =SUM(XEH9:XEH28) -> 1
C32: Sector | E32: Industry | I32: Scenario | J32: Current | K32: Simulation | L32: Equal WT | M32: Max μP | N32: Max μP | O32: Max μP | P32: Max μP | Q32: Min σP | R32: Min σP | S32: Min σP | T32: Max μ/σP | U32: Min σP | XEF32: Cash | XEG32: 0
B33: VOO | C33: Large blend | E33: N/A | I33: Main Constraint | J33: None | K33: None | L33: None | M33: μP <= 16% | N33: σP <= 14% | O33: σP <= 10% | P33: n/a | Q33: n/a | R33: μP <= 20% | S33: μP <= 18% | T33: n/a | U33: μ/σP = 2 | XEF33: Total C Val | XEG33: =XEG31+XEG32 -> 40275.367
B34: BAC | C34: Financial Services | E34: Banks | J34: --------------------------------------------------------------------------------------------------------------Portfolio Weights----------------------------------------------------------------------------------------------------------------------
B35: TSLA | C35: Consumer Cyclical | E35: Auto Manufacturer | I35: VOO | J35: =XEH9 -> 0.10776749 | K35: =G5 -> 0.10774474 | L35: 0.05 | M35: 0.11124072 | N35: 0.015 | O35: 0.015 | P35: 0.065 | Q35: 0.062101471 | R35: 0.015 | S35: 0.033242567 | T35: 0.056337418 | U35: 0.015
B36: O | C36: Real Estate | E36: REIT | I36: BAC | J36: =XEH10 -> 0.10971247 | K36: =G6 -> 0.10968931 | L36: 0.05 | M36: 0.076117907 | N36: 0.015 | O36: 0.015 | P36: 0.065 | Q36: 0.12 | R36: 0.015 | S36: 0.12 | T36: 0.12 | U36: 0.12
B37: VZ | C37: Communication Services | E37: Telecom | I37: TSLA | J37: =XEH21 -> 0.029250343 | K37: =G14 -> 0.020446893 | L37: 0.05 | M37: 0.015 | N37: 0.12 | O37: 0.058251972 | P37: 0.12 | Q37: 0.015 | R37: 0.046767986 | S37: 0.015 | T37: 0.015 | U37: 0.015
B38: AMZN | C38: Consumer Cyclical | E38: Internet | I38: O | J38: =XEH14 -> 0.06855973 | K38: =G9 -> 0.048206472 | L38: 0.05 | M38: 0.03035951 | N38: 0.015 | O38: 0.015 | P38: 0.12 | Q38: 0.015 | R38: 0.015 | S38: 0.015 | T38: 0.015 | U38: 0.015
B39: SBUX | C39: Consumer Cyclical | E39: Restaurants | I39: VZ | J39: =XEH16 -> 0.055187372 | K39: =G12 -> 0.055175721 | L39: 0.05 | M39: 0.034901224 | N39: 0.015 | O39: 0.038503826 | P39: 0.12 | Q39: 0.12 | R39: 0.089076084 | S39: 0.12 | T39: 0.12 | U39: 0.12
B40: DIA | C40: Large blend | E40: N/A | I40: AMZN | J40: =XEH13 -> 0.071549441 | K40: =G8 -> 0.071534336 | L40: 0.05 | M40: 0.035230068 | N40: 0.015 | O40: 0.015 | P40: 0.12 | Q40: 0.035 | R40: 0.015 | S40: 0.04027353 | T40: 0.051669185 | U40: 0.035
B41: GOOGL | C41: Technology | E41: Internet | I41: SBUX | J41: =XEH17 -> 0.047218393 | K41: =G10 -> 0.047208425 | L41: 0.05 | M41: 0.035868162 | N41: 0.015 | O41: 0.015 | P41: -0.13862172 | Q41: 0.12 | R41: 0.015 | S41: 0.015 | T41: 0.015 | U41: 0.12
B42: CRM | C42: Technology | E42: Software | I42: DIA | J42: =XEH15 -> 0.062008765 | K42: =G11 -> 0.061995674 | L42: 0.05 | M42: 0.073759283 | N42: 0.079231866 | O42: 0.015 | P42: 0.12 | Q42: 0.020489902 | R42: 0.015 | S42: 0.060650751 | T42: 0.06664723 | U42: 0.015
B43: CVX | C43: Energy | E43: Oil and Gas | I43: GOOGL | J43: =XEH24 -> 0.040147756 | K43: =G19 -> 0.04013928 | L43: 0.05 | M43: 0.070134178 | N43: 0.05 | O43: 0.040904637 | P43: 0.12 | Q43: 0.015 | R43: 0.0458487 | S43: 0.015 | T43: 0.015 | U43: 0.015
B44: AMD | C44: Technology | E44: Semiconductors | I44: CRM | J44: =XEH18 -> 0.023533491 | K44: =G15 -> 0.023528523 | L44: 0.05 | M44: 0.039059217 | N44: 0.015 | O44: 0.015 | P44: -0.054999996 | Q44: 0.015 | R44: 0.015 | S44: 0.015 | T44: 0.015 | U44: 0.036148424
B45: LULU | C45: Consumer Cyclical | E45: Retail | I45: CVX | J45: =XEH19 -> 0.038584232 | K45: =G16 -> 0.038576087 | L45: 0.05 | M45: 0.031969034 | N45: 0.015 | O45: 0.065 | P45: 0.065 | Q45: 0.065 | R45: 0.065 | S45: 0.065 | T45: 0.065 | U45: 0.022467367
B46: LMT | C46: Industrials | E46: Aerospace & Defense | I46: AMD | J46: =XEH23 -> 0.066975181 | K46: =G17 -> 0.066961041 | L46: 0.05 | M46: 0.015 | N46: 0.12 | O46: 0.12 | P46: 0.12 | Q46: 0.059702936 | R46: 0.12 | S46: 0.072397484 | T46: 0.065346171 | U46: 0.015
B47: UPS | C47: Industrials | E47: Freight & Logistics | I47: LULU | J47: =XEH22 -> 0.019864003 | K47: =G18 -> 0.019859809 | L47: 0.05 | M47: 0.04167562 | N47: 0.015 | O47: 0.015 | P47: 0.083621719 | Q47: 0.015 | R47: 0.015 | S47: 0.015 | T47: 0.015 | U47: 0.015
B48: XOM | C48: Energy | E48: Oil and Gas | I48: LMT | J48: =XEH25 -> 0.02603115 | K48: =G20 -> 0.026025655 | L48: 0.05 | M48: 0.032548865 | N48: 0.015 | O48: 0.015 | P48: 0.12 | Q48: 0.015 | R48: 0.015 | S48: 0.015 | T48: 0.015 | U48: 0.015
B49: COST | C49: Consumer Defense | E49: Discount Store | I49: UPS | J49: =XEH27 -> 0.021799482 | K49: =G22 -> 0.02179488 | L49: 0.05 | M49: 0.039338588 | N49: 0.015 | O49: 0.015 | P49: -0.59000008 | Q49: 0.015 | R49: 0.015 | S49: 0.015 | T49: 0.015 | U49: 0.10671309
B50: V | C50: Financial Services | E50: Credit Services | I50: XOM | J50: =XEH20 -> 0.037031253 | K50: =G21 -> 0.044456456 | L50: 0.05 | M50: 0.030434845 | N50: 0.12 | O50: 0.12 | P50: 0.12 | Q50: 0.12 | R50: 0.12 | S50: 0.12 | T50: 0.12 | U50: 0.12
B51: SO | C51: Utilities | E51: Electricity | I51: COST | J51: =XEH11 -> 0.070515558 | K51: =G7 -> 0.070500671 | L51: 0.05 | M51: 0.027 | N51: 0.12 | O51: 0.12 | P51: 0.12 | Q51: 0.015 | R51: 0.12 | S51: 0.048435672 | T51: 0.015 | U51: 0.015 | W51: Adjusted Variance-Covariance Matrix
B52: DUK | C52: Utilities | E52: Electricity | I52: V | J52: =XEH12 -> 0.067850902 | K52: =G13 -> 0.067836578 | L52: 0.05 | M52: 0.10888209 | N52: 0.12 | O52: 0.10233957 | P52: 0.12 | Q52: 0.015 | R52: 0.058307172 | S52: 0.015 | T52: 0.015 | U52: 0.015 | X52: VOO | Y52: BAC | Z52: TSLA | AA52: O | AB52: VZ | AC52: AMZN | AD52: SBUX | AE52: DIA | AF52: GOOGL | AG52: CRM | AH52: CVX | AI52: AMD | AJ52: LULU | AK52: LMT | AL52: UPS | AM52: XOM | AN52: COST | AO52: V | AP52: SO | AQ52: DUK
I53: SO | J53: =XEH26 -> 0.022149602 | K53: =G24 -> 0.026467996 | L53: 0.05 | M53: 0.12 | N53: 0.090768134 | O53: 0.065 | P53: 0.12 | Q53: 0.022705691 | R53: 0.065 | S53: 0.065 | T53: 0.065 | U53: 0.049671122 | W53: VOO | X53: =XEA93 -> 0.012095617 | Y53: =XEB93 -> 0.0088007254 | Z53: =XEC93 -> 0.03989283 | AA53: =XED93 -> 0.019137672 | AB53: =XEE93 -> -0.002567138 | AC53: =XEF93 -> -0.004468794 | AD53: =XEG93 -> 0.0062369051 | AE53: =XEH93 -> 0.020880219 | ... AQ53: =XET93 -> 0.0012340001
B54: Portfolio Sector Weights | I54: DUK | J54: =XEH28 -> 0.014263386 | K54: =G23 -> 0.031851457 | L54: 0.05 | M54: 0.031480692 | N54: 0.015 | O54: 0.12 | P54: 0.065 | Q54: 0.12 | R54: 0.12 | S54: 0.12 | T54: 0.12 | U54: 0.12 | W54: BAC | X54: =XEA94 -> 0.0088007254 | Y54: =XEB94 -> 0.0086613715 | Z54: =XEC94 -> 0.018848336 | AA54: =XED94 -> 0.016995269 | AB54: =XEE94 -> -0.0014594892 | AC54: =XEF94 -> -0.0037496198 | AD54: =XEG94 -> 0.0050572151 | AE54: =XEH94 -> 0.016264436 | ... AQ54: =XET94 -> 0.00024879583
C55: Technology | D55: =J61 -> 0.13065643 | I55: Total | J55: =SUM(J35:J54) -> 1 | K55: =SUM(K35:K54) -> 1 | L55: =SUM(L35:L54) -> 1 | M55: =SUM(M35:M54) -> 1 | N55: =SUM(N35:N54) -> 1 | O55: =SUM(O35:O54) -> 1 | P55: =SUM(P35:P54) -> 0.99999992 | Q55: =SUM(Q35:Q54) -> 1 | ... U55: =SUM(U35:U54) -> 1 | W55: TSLA | X55: =XEA95 -> 0.03989283 | Y55: =XEB95 -> 0.018848336 | Z55: =XEC95 -> 0.42296395 | AA55: =XED95 -> 0.026370921 | AB55: =XEE95 -> 0.027549055 | AC55: =XEF95 -> -0.050742286 | AD55: =XEG95 -> 0.0079207887 | AE55: =XEH95 -> 0.1203846 | ... AQ55: =XET95 -> -0.0011733514
C56: Consumer Cyclical | D56: =J62 -> 0.16788218 | I56: μP | J56: {=MMULT(TRANSPOSE(J35:J54),$S$5:$S$24)} -> 0.17665579 | K56: {=MMULT(TRANSPOSE(K35:K54),$S$5:$S$24)} -> 0.17472416 | L56: {=MMULT(TRANSPOSE(L35:L54),$S$5:$S$24)} -> 0.16741127 | M56: {=MMULT(TRANSPOSE(M35:M54),$S$5:$S$24)} -> 0.15886877 | N56: {=MMULT(TRANSPOSE(N35:N54),$S$5:$S$24)} -> 0.2245317 | O56: {=MMULT(TRANSPOSE(O35:O54),$S$5:$S$24)} -> 0.20472673 | P56: {=MMULT(TRANSPOSE(P35:P54),$S$5:$S$24)} -> 0.27173265 | Q56: {=MMULT(TRANSPOSE(Q35:Q54),$S$5:$S$24)} -> 0.15716809 | ... U56: {=MMULT(TRANSPOSE(U35:U54),$S$5:$S$24)} -> 0.13610044 | W56: O | X56: =XEA96 -> 0.019137672 | Y56: =XEB96 -> 0.016995269 | Z56: =XEC96 -> 0.026370921 | AA56: =XED96 -> 0.050753223 | AB56: =XEE96 -> -0.0036313825 | AC56: =XEF96 -> 0.00905138 | AD56: =XEG96 -> 0.010417605 | AE56: =XEH96 -> 0.018768828 | ... AQ56: =XET96 -> 0.0086489277
C57: Large Blend | D57: =J63 -> 0.16977626 | I57: σP | J57: {=SQRT(MMULT(MMULT(TRANSPOSE(J35:J54),$X$53:$AQ$72),J35:J54))} -> 0.10194357 | K57: {=SQRT(MMULT(MMULT(TRANSPOSE(K35:K54),$X$53:$AQ$72),K35:K54))} -> 0.095937834 | L57: {=SQRT(MMULT(MMULT(TRANSPOSE(L35:L54),$X$53:$AQ$72),L35:L54))} -> 0.10467777 | M57: {=SQRT(MMULT(MMULT(TRANSPOSE(M35:M54),$X$53:$AQ$72),M35:M54))} -> 0.10075476 | N57: {=SQRT(MMULT(MMULT(TRANSPOSE(N35:N54),$X$53:$AQ$72),N35:N54))} -> 0.14000003 | O57: {=SQRT(MMULT(MMULT(TRANSPOSE(O35:O54),$X$53:$AQ$72),O35:O54))} -> 0.10000012 | P57: {=SQRT(MMULT(MMULT(TRANSPOSE(P35:P54),$X$53:$AQ$72),P35:P54))} -> 0.16031711 | Q57: {=SQRT(MMULT(MMULT(TRANSPOSE(Q35:Q54),$X$53:$AQ$72),Q35:Q54))} -> 0.0654239 | ... U57: {=SQRT(MMULT(MMULT(TRANSPOSE(U35:U54),$X$53:$AQ$72),U35:U54))} -> 0.068049841 | W57: VZ | X57: =XEA97 -> -0.002567138 | Y57: =XEB97 -> -0.0014594892 | Z57: =XEC97 -> 0.027549055 | AA57: =XED97 -> -0.0036313825 | AB57: =XEE97 -> 0.012588661 | AC57: =XEF97 -> 0.004897226 | AD57: =XEG97 -> -0.0031484893 | AE57: =XEH97 -> 0.0032777957 | ... AQ57: =XET97 -> 0.0031366947
C58: Communication Services | D58: =J64 -> 0.055187372 | I58: μ/σ | J58: =J56/J57 -> 1.7328781 | K58: =K56/K57 -> 1.8212227 | L58: =L56/L57 -> 1.599301 | M58: =M56/M57 -> 1.5767868 | N58: =N56/N57 -> 1.6037975 | O58: =O56/O57 -> 2.0472648 | P58: =P56/P57 -> 1.6949698 | Q58: =Q56/Q57 -> 2.402304 | ... U58: =U56/U57 -> 2.0000111 | W58: AMZN | X58: =XEA98 -> -0.004468794 | Y58: =XEB98 -> -0.0037496198 | Z58: =XEC98 -> -0.050742286 | AA58: =XED98 -> 0.00905138 | AB58: =XEE98 -> 0.004897226 | AC58: =XEF98 -> 0.029227888 | AD58: =XEG98 -> 0.0020702355 | AE58: =XEH98 -> -0.024617983 | ... AQ58: =XET98 -> 0.010570992
C59: Real Estate | D59: =J65 -> 0.06855973 | I59: βP | J59: =SUM((J35*$U$5),(J42*$U$6),(J37*$U$7),(J36*$U$8),(J41*$U$9),(J38*$U$10),(J39*$U$11),(J43*$U$13),(J40*$U$12),(J44*$U$14),(J45*$U$15),(J46*$U$16),(J47*$U$17),(J48*$U$18),(J49*$U$19),(J50*$U$20),(J51*$U$21),(J52*$U$22),(J53*$U$23),(J54*$U$24)) -> 0.99247421 | K59: =SUM((K35*$U$5),(K42*$U$6),(K37*$U$7),(K36*$U$8),(K41*$U$9),(K38*$U$10),(K39*$U$11),(K43*$U$13),(K40*$U$12),(K44*$U$14),(K45*$U$15),(K46*$U$16),(K47*$U$17),(K48*$U$18),(K49*$U$19),(K50*$U$20),(K51*$U$21),(K52*$U$22),(K53*$U$23),(K54*$U$24)) -> 0.97077701 | L59: =SUM((L35*$U$5),(L42*$U$6),(L37*$U$7),(L36*$U$8),(L41*$U$9),(L38*$U$10),(L39*$U$11),(L43*$U$13),(L40*$U$12),(L44*$U$14),(L45*$U$15),(L46*$U$16),(L47*$U$17),(L48*$U$18),(L49*$U$19),(L50*$U$20),(L51*$U$21),(L52*$U$22),(L53*$U$23),(L54*$U$24)) -> 0.90814 | M59: =SUM((M35*$U$5),(M42*$U$6),(M37*$U$7),(M36*$U$8),(M41*$U$9),(M38*$U$10),(M39*$U$11),(M43*$U$13),(M40*$U$12),(M44*$U$14),(M45*$U$15),(M46*$U$16),(M47*$U$17),(M48*$U$18),(M49*$U$19),(M50*$U$20),(M51*$U$21),(M52*$U$22),(M53*$U$23),(M54*$U$24)) -> 0.83815642 | N59: =SUM((N35*$U$5),(N42*$U$6),(N37*$U$7),(N36*$U$8),(N41*$U$9),(N38*$U$10),(N39*$U$11),(N43*$U$13),(N40*$U$12),(N44*$U$14),(N45*$U$15),(N46*$U$16),(N47*$U$17),(N48*$U$18),(N49*$U$19),(N50*$U$20),(N51*$U$21),(N52*$U$22),(N53*$U$23),(N54*$U$24)) -> 1.0397006 | O59: =SUM((O35*$U$5),(O42*$U$6),(O37*$U$7),(O36*$U$8),(O41*$U$9),(O38*$U$10),(O39*$U$11),(O43*$U$13),(O40*$U$12),(O44*$U$14),(O45*$U$15),(O46*$U$16),(O47*$U$17),(O48*$U$18),(O49*$U$19),(O50*$U$20),(O51*$U$21),(O52*$U$22),(O53*$U$23),(O54*$U$24)) -> 0.90195999 | P59: =SUM((P35*$U$5),(P42*$U$6),(P37*$U$7),(P36*$U$8),(P41*$U$9),(P38*$U$10),(P39*$U$11),(P43*$U$13),(P40*$U$12),(P44*$U$14),(P45*$U$15),(P46*$U$16),(P47*$U$17),(P48*$U$18),(P49*$U$19),(P50*$U$20),(P51*$U$21),(P52*$U$22),(P53*$U$23),(P54*$U$24)) -> 0.80749478 | Q59: =SUM((Q35*$U$5),(Q42*$U$6),(Q37*$U$7),(Q36*$U$8),(Q41*$U$9),(Q38*$U$10),(Q39*$U$11),(Q43*$U$13),(Q40*$U$12),(Q44*$U$14),(Q45*$U$15),(Q46*$U$16),(Q47*$U$17),(Q48*$U$18),(Q49*$U$19),(Q50*$U$20),(Q51*$U$21),(Q52*$U$22),(Q53*$U$23),(Q54*$U$24)) -> 0.79080469 | ... U59: =SUM((U35*$U$5),(U42*$U$6),(U37*$U$7),(U36*$U$8),(U41*$U$9),(U38*$U$10),(U39*$U$11),(U43*$U$13),(U40*$U$12),(U44*$U$14),(U45*$U$15),(U46*$U$16),(U47*$U$17),(U48*$U$18),(U49*$U$19),(U50*$U$20),(U51*$U$21),(U52*$U$22),(U53*$U$23),(U54*$U$24)) -> 0.73433092 | W59: SBUX | X59: =XEA99 -> 0.0062369051 | Y59: =XEB99 -> 0.0050572151 | Z59: =XEC99 -> 0.0079207887 | AA59: =XED99 -> 0.010417605 | AB59: =XEE99 -> -0.0031484893 | AC59: =XEF99 -> 0.0020702355 | AD59: =XEG99 -> 0.010879024 | AE59: =XEH99 -> 0.015839844 | ... AQ59: =XET99 -> 0.0018618656
C60: Financial Services | D60: =J66 -> 0.17756337 | J60: --------------------------------------------------------------------------------------------------------------Sector Weights---------------------------------------------------------------------------------------------------------------------- | W60: DIA | X60: =XEA100 -> 0.020880219 | Y60: =XEB100 -> 0.016264436 | Z60: =XEC100 -> 0.1203846 | AA60: =XED100 -> 0.018768828 | AB60: =XEE100 -> 0.0032777957 | AC60: =XEF100 -> -0.024617983 | AD60: =XEG100 -> 0.015839844 | AE60: =XEH100 -> 0.082086038 | ... AQ60: =XET100 -> -0.0026375617
C61: Energy | D61: =J67 -> 0.075615486 | I61: Technology | J61: =SUM(J43,J44,J46) -> 0.13065643 | K61: =SUM(K43,K44,K46) -> 0.13062884 | L61: =SUM(L43,L44,L46) -> 0.15 | M61: =SUM(M43,M44,M46) -> 0.12419339 | N61: =SUM(N43,N44,N46) -> 0.185 | O61: =SUM(O43,O44,O46) -> 0.17590464 | P61: =SUM(P43,P44,P46) -> 0.185 | Q61: =SUM(Q43,Q44,Q46) -> 0.089702936 | ... U61: =SUM(U43,U44,U46) -> 0.066148424 | W61: GOOGL | X61: =XEA101 -> 0.023376441 | Y61: =XEB101 -> 0.016576281 | Z61: =XEC101 -> 0.07440706 | AA61: =XED101 -> 0.039562496 | AB61: =XEE101 -> -0.009852775 | AC61: =XEF101 -> -0.0068914227 | AD61: =XEG101 -> 0.013733882 | AE61: =XEH101 -> 0.042294992 | ... AQ61: =XET101 -> 0.0032552748
C62: Industrials | D62: =J68 -> 0.047830632 | I62: Consumer Cyclical | J62: =SUM(J37,J40,J41,J47) -> 0.16788218 | K62: =SUM(K37,K40,K41,K47) -> 0.15904946 | L62: =SUM(L37,L40,L41,L47) -> 0.2 | M62: =SUM(M37,M40,M41,M47) -> 0.12777385 | N62: =SUM(N37,N40,N41,N47) -> 0.165 | O62: =SUM(O37,O40,O41,O47) -> 0.10325197 | P62: =SUM(P37,P40,P41,P47) -> 0.185 | Q62: =SUM(Q37,Q40,Q41,Q47) -> 0.185 | ... U62: =SUM(U37,U40,U41,U47) -> 0.185 | W62: CRM | X62: =XEA102 -> 0.014521566 | Y62: =XEB102 -> 0.011527224 | Z62: =XEC102 -> 0.061449049 | AA62: =XED102 -> 0.010666938 | AB62: =XEE102 -> 0.0055271527 | AC62: =XEF102 -> -0.013708743 | AD62: =XEG102 -> 0.015254069 | AE62: =XEH102 -> 0.065792324 | ... AQ62: =XET102 -> -0.0029370354
C63: Consumer Defense | D63: =J69 -> 0.070515558 | I63: Large Blend | J63: =SUM(J35,J42) -> 0.16977626 | K63: =SUM(K35,K42) -> 0.16974041 | L63: =SUM(L35,L42) -> 0.1 | M63: =SUM(M35,M42) -> 0.185 | N63: =SUM(N35,N42) -> 0.094231866 | O63: =SUM(O35,O42) -> 0.03 | P63: =SUM(P35,P42) -> 0.185 | Q63: =SUM(Q35,Q42) -> 0.082591373 | ... U63: =SUM(U35,U42) -> 0.03 | W63: CVX | X63: =XEA103 -> -0.0020846986 | Y63: =XEB103 -> 0.0029220003 | Z63: =XEC103 -> -0.06110264 | AA63: =XED103 -> 0.017890399 | AB63: =XEE103 -> -0.0014666184 | AC63: =XEF103 -> 0.013502948 | AD63: =XEG103 -> -0.0061053443 | AE63: =XEH103 -> -0.03442573 | ... AQ63: =XET103 -> 0.0029411956
C64: Utilities | D64: =J70 -> 0.036412989 | I64: Communication Services | J64: =SUM(J39) -> 0.055187372 | K64: =SUM(K39) -> 0.055175721 | L64: =SUM(L39) -> 0.05 | M64: =SUM(M39) -> 0.034901224 | N64: =SUM(N39) -> 0.015 | O64: =SUM(O39) -> 0.038503826 | P64: =SUM(P39) -> 0.12 | Q64: =SUM(Q39) -> 0.12 | ... U64: =SUM(U39) -> 0.12 | W64: AMD | X64: =XEA104 -> 0.011014965 | Y64: =XEB104 -> -9.6950088e-05 | Z64: =XEC104 -> 0.062466646 | AA64: =XED104 -> -0.0054466784 | AB64: =XEE104 -> -0.024446786 | AC64: =XEF104 -> -0.0026707614 | AD64: =XEG104 -> 0.026525225 | AE64: =XEH104 -> 0.033372022 | ... AQ64: =XET104 -> -0.0029539931
D65: =SUM(D55:D64) -> 1 | I65: Real Estate | J65: =SUM(J38) -> 0.06855973 | K65: =SUM(K38) -> 0.048206472 | L65: =SUM(L38) -> 0.05 | M65: =SUM(M38) -> 0.03035951 | N65: =SUM(N38) -> 0.015 | O65: =SUM(O38) -> 0.015 | P65: =SUM(P38) -> 0.12 | Q65: =SUM(Q38) -> 0.015 | ... U65: =SUM(U38) -> 0.015 | W65: LULU | X65: =XEA105 -> -0.00043980075 | Y65: =XEB105 -> 0.00028828677 | Z65: =XEC105 -> 0.055901842 | AA65: =XED105 -> -0.020781048 | AB65: =XEE105 -> 0.035635431 | AC65: =XEF105 -> -0.0051217112 | AD65: =XEG105 -> 0.0076903936 | AE65: =XEH105 -> 0.04787861 | ... AQ65: =XET105 -> -0.0049768775
I66: Financial Services | J66: =SUM(J52,J36) -> 0.17756337 | K66: =SUM(K52,K36) -> 0.17752588 | L66: =SUM(L52,L36) -> 0.1 | M66: =SUM(M52,M36) -> 0.185 | N66: =SUM(N52,N36) -> 0.135 | O66: =SUM(O52,O36) -> 0.11733957 | P66: =SUM(P52,P36) -> 0.185 | Q66: =SUM(Q52,Q36) -> 0.135 | ... U66: =SUM(U52,U36) -> 0.135 | W66: LMT | X66: =XEA106 -> 0.0067909854 | Y66: =XEB106 -> 0.01134648 | Z66: =XEC106 -> -0.035901196 | AA66: =XED106 -> 0.025344648 | AB66: =XEE106 -> 0.0023765658 | AC66: =XEF106 -> 0.0093659131 | AD66: =XEG106 -> 0.0043661656 | AE66: =XEH106 -> -0.012509141 | ... AQ66: =XET106 -> 0.0036451752
I67: Energy | J67: =SUM(J45,J50) -> 0.075615486 | K67: =SUM(K45,K50) -> 0.083032543 | L67: =SUM(L45,L50) -> 0.1 | M67: =SUM(M45,M50) -> 0.062403879 | N67: =SUM(N45,N50) -> 0.135 | O67: =SUM(O45,O50) -> 0.185 | P67: =SUM(P45,P50) -> 0.185 | Q67: =SUM(Q45,Q50) -> 0.185 | ... U67: =SUM(U45,U50) -> 0.14246737 | W67: UPS | X67: =XEA107 -> 0.0069238614 | Y67: =XEB107 -> 0.0068607378 | Z67: =XEC107 -> 0.08471569 | AA67: =XED107 -> 0.011008952 | AB67: =XEE107 -> 0.0090556505 | AC67: =XEF107 -> -0.011021972 | AD67: =XEG107 -> -0.0025307651 | AE67: =XEH107 -> 0.012905638 | ... AQ67: =XET107 -> -0.00350569
I68: Industrials | J68: =SUM(J48,J49) -> 0.047830632 | K68: =SUM(K48,K49) -> 0.047820534 | L68: =SUM(L48,L49) -> 0.1 | M68: =SUM(M48,M49) -> 0.071887453 | N68: =SUM(N48,N49) -> 0.03 | O68: =SUM(O48,O49) -> 0.03 | P68: =SUM(P48,P49) -> -0.47000008 | Q68: =SUM(Q48,Q49) -> 0.03 | ... U68: =SUM(U48,U49) -> 0.12171309 | W68: XOM | X68: =XEA108 -> -0.0047378143 | Y68: =XEB108 -> 0.0010779279 | Z68: =XEC108 -> -0.087771249 | AA68: =XED108 -> 0.016730136 | AB68: =XEE108 -> -0.0051612985 | AC68: =XEF108 -> 0.01419749 | AD68: =XEG108 -> -0.010929633 | AE68: =XEH108 -> -0.050446595 | ... AQ68: =XET108 -> 0.0018117701
I69: Consumer Defensive | J69: =SUM(J51) -> 0.070515558 | K69: =SUM(K51) -> 0.070500671 | L69: =SUM(L51) -> 0.05 | M69: =SUM(M51) -> 0.027 | N69: =SUM(N51) -> 0.12 | O69: =SUM(O51) -> 0.12 | P69: =SUM(P51) -> 0.12 | Q69: =SUM(Q51) -> 0.015 | ... U69: =SUM(U51) -> 0.015 | W69: COST | X69: =XEA109 -> 0.012047011 | Y69: =XEB109 -> 0.0094057848 | Z69: =XEC109 -> 0.038660723 | AA69: =XED109 -> 0.018910592 | AB69: =XEE109 -> 0.0052390247 | AC69: =XEF109 -> -0.0034993484 | AD69: =XEG109 -> 0.0055712843 | AE69: =XEH109 -> 0.023639476 | ... AQ69: =XET109 -> 0.00088314386
I70: Utilities | J70: =SUM(J53,J54) -> 0.036412989 | K70: =SUM(K53,K54) -> 0.058319453 | L70: =SUM(L53,L54) -> 0.1 | M70: =SUM(M53,M54) -> 0.15148069 | N70: =SUM(N53,N54) -> 0.10576813 | O70: =SUM(O53,O54) -> 0.185 | P70: =SUM(P53,P54) -> 0.185 | Q70: =SUM(Q53,Q54) -> 0.14270569 | ... U70: =SUM(U53,U54) -> 0.16967112 | W70: V | X70: =XEA110 -> 0.0096288346 | Y70: =XEB110 -> 0.010888802 | Z70: =XEC110 -> 0.005320121 | AA70: =XED110 -> 0.01993609 | AB70: =XEE110 -> 0.0046324304 | AC70: =XEF110 -> 0.0024535247 | AD70: =XEG110 -> 0.0091253375 | AE70: =XEH110 -> 0.018675044 | ... AQ70: =XET110 -> 0.0026453401
I71: Total | J71: =SUM(J61:J70) -> 1 | K71: =SUM(K61:K70) -> 1 | L71: =SUM(L61:L70) -> 1 | M71: =SUM(M61:M70) -> 1 | N71: =SUM(N61:N70) -> 1 | O71: =SUM(O61:O70) -> 1 | P71: =SUM(P61:P70) -> 0.99999992 | Q71: =SUM(Q61:Q70) -> 1 | ... U71: =SUM(U61:U70) -> 1 | W71: SO | X71: =XEA111 -> 0.0034553939 | Y71: =XEB111 -> 0.0010892993 | Z71: =XEC111 -> -0.013390588 | AA71: =XED111 -> 0.013011205 | AB71: =XEE111 -> 0.0046282722 | AC71: =XEF111 -> 0.017522646 | AD71: =XEG111 -> 0.0047058735 | AE71: =XEH111 -> -0.0098297076 | ... AQ71: =XET111 -> 0.0083806339
W72: DUK | X72: =XEA112 -> 0.0012340001 | Y72: =XEB112 -> 0.00024879583 | Z72: =XEC112 -> -0.0011733514 | AA72: =XED112 -> 0.0086489277 | AB72: =XEE112 -> 0.0031366947 | AC72: =XEF112 -> 0.010570992 | AD72: =XEG112 -> 0.0018618656 | AE72: =XEH112 -> -0.0026375617 | ... AQ72: =XET112 -> 0.0059043472
XDY79: Adjusted incl COST, V, SO, & DUK
XDZ80: {=TRANSPOSE(I5:I24)} -> VOO | XEA80: DIA | XEB80: TSLA | XEC80: BAC | XED80: SBUX | XEE80: O | XEF80: VZ | XEG80: AMZN | XEH80: GOOGL | XEI80: CRM | XEJ80: CVX | XEK80: AMD | XEL80: LULU | XEM80: LMT | XEN80: UPS | XEO80: XOM | XEP80: COST | XEQ80: V | XER80: SO | XES80: DUK
XDY81: 2017 | XDZ81: {=TRANSPOSE('Data & Analysis'!AC5:AK24)} -> 0.25263356 | XEA81: 0.31990622 | XEB81: 0.34071492 | XEC81: 0.37630852 | XED81: 0.068469403 | XEE81: -0.0033746044 | XEF81: 0.20947157 | XEG81: 0.5664283 | XEH81: 0.36564515 | XEI81: 0.36461473 | XEJ81: 0.20442238 | XEK81: 0.28139426 | XEL81: 0.14712178 | XEM81: 0.39590723 | XEN81: 0.21877248 | XEO81: 0.12596392 | XEP81: 0.27401025 | XEQ81: 0.41970703 | XER81: 0.023095715 | XES81: 0.10045711
XDY82: =XDY81+1 -> 2018 | XDZ82: -0.0031294809 | XEA82: 9.7742591e-05 | XEB82: -0.14313341 | XEC82: -0.076390847 | XED82: 0.22688187 | XEE82: 0.35510338 | XEF82: 0.1260411 | XEG82: 0.16951124 | XEH82: -0.048866815 | XEI82: 0.28832505 | XEJ82: -0.00011143924 | XEK82: 0.5746816 | XEL82: 0.63653015 | XEM82: -0.14416424 | XEN82: -0.11318196 | XEO82: -0.075658468 | XEP82: 0.11831671 | XEQ82: 0.096729626 | XER82: 0.18896812 | XES82: 0.21050135
XDY83: =XDY82+1 -> 2019 | XDZ83: 0.21657086 | XEA83: 0.16704114 | XEB83: 0.75080756 | XEC83: 0.18782742 | XED83: 0.25734346 | XEE83: 0.21499874 | XEF83: 0.17388834 | XEG83: 0.15591116 | XEH83: 0.24104707 | XEI83: 0.18200012 | XEJ83: 0.027877579 | XEK83: 0.65515472 | XEL83: 0.48216636 | XEM83: 0.4403192 | XEN83: 0.060653471 | XEO83: -0.048546703 | XEP83: 0.37186299 | XEQ83: 0.39965295 | XER83: 0.45795937 | XES83: 0.19606773
XDY84: =XDY83+1 -> 2020 | XDZ84: 0.17493662 | XEA84: 0.10187341 | XEB84: 1.8081111 | XEC84: -0.04856196 | XED84: 0.17168137 | XEE84: -0.17896252 | XEF84: 0.019774755 | XEG84: 0.46754891 | XEH84: 0.24320795 | XEI84: 0.21288099 | XEJ84: -0.10254983 | XEK84: 0.60000486 | XEL84: 0.31699061 | XEM84: -0.22595726 | XEN84: 0.46855365 | XEO84: -0.1591883 | XEP84: 0.21461306 | XEQ84: -0.016515347 | XER84: -0.085043349 | XES84: 0.052736296
XDY85: =XDY84+1 -> 2021 | XDZ85: 0.22327455 | XEA85: 0.19203014 | XEB85: 0.16589307 | XEC85: 0.47975337 | XED85: 0.052102103 | XEE85: 0.2826536 | XEF85: 0.075536227 | XEG85: -0.06934493 | XEH85: 0.39267333 | XEI85: 0.030878903 | XEJ85: 0.52968203 | XEK85: 0.28823657 | XEL85: 0.015337539 | XEM85: 0.24940204 | XEN85: 0.31079914 | XEO85: 0.63795981 | XEP85: 0.37391829 | XEQ85: 0.16946301 | XER85: 0.24864438 | XES85: 0.19234302
XDY86: =XDY85+1 -> 2022 | XDZ86: -0.069349585 | XEA86: 0.009112192 | XEB86: -0.58920966 | XEC86: -0.21369915 | XED86: 0.14725009 | XEE86: 0.071207577 | XEF86: -0.12091901 | XEG86: -0.37177418 | XEH86: -0.31407281 | XEI86: -0.32567972 | XEJ86: 0.35283573 | XEK86: -0.41890291 | XEL86: -0.08396538 | XEM86: 0.22644398 | XEN86: -0.018299312 | XEO86: 0.49536374 | XEP86: 0.025568673 | XEQ86: 0.032196975 | XER86: 0.055520653 | XES86: 0.055722029
XDY87: =XDY86+1 -> 2023 | XDZ87: 0.20317025 | XEA87: 0.15036946 | XEB87: 0.078095755 | XEC87: 0.015947382 | XED87: -0.11495003 | XEE87: -0.10759247 | XEF87: 0.15773565 | XEG87: 0.40872428 | XEH87: 0.34888182 | XEI87: 0.51488428 | XEJ87: -0.084009611 | XEK87: 0.80263092 | XEL87: 0.39124385 | XEM87: -0.019885852 | XEN87: -0.17837337 | XEO87: -0.049823384 | XEP87: 0.3643055 | XEQ87: 0.1862604 | XER87: 0.10862423 | XES87: 0.020597051
XDY88: =XDY87+1 -> 2024 | XDZ88: 0.24575445 | XEA88: 0.18746589 | XEB88: 0.77024071 | XEC88: 0.35553863 | XED88: 0.19366658 | XEE88: 0.11423381 | XEF88: 0.06191901 | XEG88: 0.42621062 | XEH88: 0.38244328 | XEI88: 0.20553179 | XEJ88: 0.098241008 | XEK88: -0.36895797 | XEL88: -0.091351695 | XEM88: 0.12880175 | XEN88: -0.1116137 | XEO88: 0.10815792 | XEP88: 0.35411293 | XEQ88: 0.23770658 | XER88: 0.25899571 | XES88: 0.23311266
XDY89: 2025 | XDZ89: 0.22730931 | XEA89: 0.18390247 | XEB89: 0.017736 | XEC89: 0.26063473 | XED89: 0.0094611099 | XEE89: 0.24007396 | XEF89: 0.23916904 | XEG89: 0.010296855 | XEH89: 0.55502507 | XEI89: -0.75655115 | XEJ89: 0.19563423 | XEK89: 1.5374652 | XEL89: -1.2876099 | XEM89: 0.12960543 | XEN89: 0.056620972 | XEO89: 0.29773109 | XEP89: -0.025405629 | XEQ89: 0.011705917 | XER89: 0.19665352 | XES89: 0.19547871
XEA92: Column 1 | XEB92: Column 2 | XEC92: Column 3 | XED92: Column 4 | XEE92: Column 5 | XEF92: Column 6 | XEG92: Column 7 | XEH92: Column 8 | XEI92: Column 9 | XEJ92: Column 10 | XEK92: Column 11 | XEL92: Column 12 | XEM92: Column 13 | XEN92: Column 14 | XEO92: Column 15 | XEP92: Column 16 | XEQ92: Column 17 | XER92: Column 18 | XES92: Column 19 | XET92: Column 20
XDZ93: Column 1 | XEA93: =VARP(Optimization!$XDZ$81:$XDZ$89) -> 0.012095617 | XEB93: 0.0088007254 | XEC93: 0.03989283 | XED93: 0.019137672 | XEE93: -0.002567138 | XEF93: -0.004468794 | XEG93: 0.0062369051 | XEH93: 0.020880219 | XEI93: 0.023376441 | XEJ93: 0.014521566 | XEK93: -0.0020846986 | XEL93: 0.011014965 | XEM93: -0.00043980075 | XEN93: 0.0067909854 | XEO93: 0.0069238614 | XEP93: -0.0047378143 | XEQ93: 0.012047011 | XER93: 0.0096288346 | XES93: 0.0034553939 | XET93: 0.0012340001
XDZ94: Column 2 | XEA94: 0.0088007254 | XEB94: =VARP(Optimization!$XEA$81:$XEA$89) -> 0.0086613715 | XEC94: 0.018848336 | XED94: 0.016995269 | XEE94: -0.0014594892 | XEF94: -0.0037496198 | XEG94: 0.0050572151 | XEH94: 0.016264436 | XEI94: 0.016576281 | XEJ94: 0.011527224 | XEK94: 0.0029220003 | XEL94: -9.6950088e-05 | XEM94: 0.00028828677 | XEN94: 0.01134648 | XEO94: 0.0068607378 | XEP94: 0.0010779279 | XEQ94: 0.0094057848 | XER94: 0.010888802 | XES94: 0.0010892993 | XET94: 0.00024879583
XDZ95: Column 3 | XEA95: 0.03989283 | XEB95: 0.018848336 | XEC95: =VARP(Optimization!$XEB$81:$XEB$89) -> 0.42296395 | XED95: 0.026370921 | XEE95: 0.027549055 | XEF95: -0.050742286 | XEG95: 0.0079207887 | XEH95: 0.1203846 | XEI95: 0.07440706 | XEJ95: 0.061449049 | XEK95: -0.06110264 | XEL95: 0.062466646 | XEM95: 0.055901842 | XEN95: -0.035901196 | XEO95: 0.08471569 | XEP95: -0.087771249 | XEQ95: 0.038660723 | XER95: 0.005320121 | XES95: -0.013390588 | XET95: -0.0011733514
XDZ96: Column 4 | XEA96: 0.019137672 | XEB96: 0.016995269 | XEC96: 0.026370921 | XED96: =VARP(Optimization!$XEC$81:$XEC$89) -> 0.050753223 | XEE96: -0.0036313825 | XEF96: 0.00905138 | XEG96: 0.010417605 | XEH96: 0.018768828 | XEI96: 0.039562496 | XEJ96: 0.010666938 | XEK96: 0.017890399 | XEL96: -0.0054466784 | XEM96: -0.020781048 | XEN96: 0.025344648 | XEO96: 0.011008952 | XEP96: 0.016730136 | XEQ96: 0.018910592 | XER96: 0.01993609 | XES96: 0.013011205 | XET96: 0.0086489277
XDZ97: Column 5 | XEA97: -0.002567138 | XEB97: -0.0014594892 | XEC97: 0.027549055 | XED97: -0.0036313825 | XEE97: =VARP(Optimization!$XED$81:$XED$89) -> 0.012588661 | XEF97: 0.004897226 | XEG97: -0.0031484893 | XEH97: 0.0032777957 | XEI97: -0.009852775 | XEJ97: 0.0055271527 | XEK97: -0.0014666184 | XEL97: -0.024446786 | XEM97: 0.035635431 | XEN97: 0.0023765658 | XEO97: 0.0090556505 | XEP97: -0.0051612985 | XEQ97: 0.0052390247 | XER97: 0.0046324304 | XES97: 0.0046282722 | XET97: 0.0031366947
XDZ98: Column 6 | XEA98: -0.004468794 | XEB98: -0.0037496198 | XEC98: -0.050742286 | XED98: 0.00905138 | XEE98: 0.004897226 | XEF98: =VARP(Optimization!$XEE$81:$XEE$89) -> 0.029227888 | XEG98: 0.0020702355 | XEH98: -0.024617983 | XEI98: -0.0068914227 | XEJ98: -0.013708743 | XEK98: 0.013502948 | XEL98: -0.0026707614 | XEM98: -0.0051217112 | XEN98: 0.0093659131 | XEO98: -0.011021972 | XEP98: 0.01419749 | XEQ98: -0.0034993484 | XER98: 0.0024535247 | XES98: 0.017522646 | XET98: 0.010570992
XDZ99: Column 7 | XEA99: 0.0062369051 | XEB99: 0.0050572151 | XEC99: 0.0079207887 | XED99: 0.010417605 | XEE99: -0.0031484893 | XEF99: 0.0020702355 | XEG99: =VARP(Optimization!$XEF$81:$XEF$89) -> 0.010879024 | XEH99: 0.015839844 | XEI99: 0.013733882 | XEJ99: 0.015254069 | XEK99: -0.0061053443 | XEL99: 0.026525225 | XEM99: 0.0076903936 | XEN99: 0.0043661656 | XEO99: -0.0025307651 | XEP99: -0.010929633 | XEQ99: 0.0055712843 | XER99: 0.0091253375 | XES99: 0.0047058735 | XET99: 0.0018618656
XDZ100: Column 8 | XEA100: 0.020880219 | XEB100: 0.016264436 | XEC100: 0.1203846 | XED100: 0.018768828 | XEE100: 0.0032777957 | XEF100: -0.024617983 | XEG100: 0.015839844 | XEH100: =VARP(Optimization!$XEG$81:$XEG$89) -> 0.082086038 | XEI100: 0.042294992 | XEJ100: 0.065792324 | XEK100: -0.03442573 | XEL100: 0.033372022 | XEM100: 0.04787861 | XEN100: -0.012509141 | XEO100: 0.012905638 | XEP100: -0.050446595 | XEQ100: 0.023639476 | XER100: 0.018675044 | XES100: -0.0098297076 | XET100: -0.0026375617
XDZ101: Column 9 | XEA101: 0.023376441 | XEB101: 0.016576281 | XEC101: 0.07440706 | XED101: 0.039562496 | XEE101: -0.009852775 | XEF101: -0.0068914227 | XEG101: 0.013733882 | XEH101: 0.042294992 | XEI101: =VARP(Optimization!$XEH$81:$XEH$89) -> 0.062325567 | XEJ101: 0.030131849 | XEK101: -0.0050311546 | XEL101: 0.032902049 | XEM101: -0.0066987905 | XEN101: 0.006540841 | XEO101: 0.010972326 | XEP101: -0.0099782444 | XEQ101: 0.022515837 | XER101: 0.015491637 | XES101: 0.00601505 | XET101: 0.0032552748
XDZ102: Column 10 | XEA102: 0.014521566 | XEB102: 0.011527224 | XEC102: 0.061449049 | XED102: 0.010666938 | XEE102: 0.0055271527 | XEF102: -0.013708743 | XEG102: 0.015254069 | XEH102: 0.065792324 | XEI102: 0.030131849 | XEJ102: =VARP(Optimization!$XEI$81:$XEI$89) -> 0.13601717 | XEK102: -0.027477668 | XEL102: 0.039471181 | XEM102: 0.07946659 | XEN102: -0.010245535 | XEO102: 0.0043889327 | XEP102: -0.039580919 | XEQ102: 0.027889737 | XER102: 0.019612461 | XES102: -0.001771877 | XET102: -0.0029370354
XDZ103: Column 11 | XEA103: -0.0020846986 | XEB103: 0.0029220003 | XEC103: -0.06110264 | XED103: 0.017890399 | XEE103: -0.0014666184 | XEF103: 0.013502948 | XEG103: -0.0061053443 | XEH103: -0.03442573 | XEI103: -0.0050311546 | XEJ103: -0.027477668 | XEK103: =VARP(Optimization!$XEJ$81:$XEJ$89) -> 0.038577053 | XEL103: -0.044451181 | XEM103: -0.030255137 | XEN103: 0.023151808 | XEO103: 0.0090693778 | XEP103: 0.048387648 | XEQ103: -0.0010832545 | XER103: 0.0015242988 | XES103: 0.0035811228 | XET103: 0.0029411956
XDZ104: Column 12 | XEA104: 0.011014965 | XEB104: -9.6950088e-05 | XEC104: 0.062466646 | XED104: -0.0054466784 | XEE104: -0.024446786 | XEF104: -0.0026707614 | XEG104: 0.026525225 | XEH104: 0.033372022 | XEI104: 0.032902049 | XEJ104: 0.039471181 | XEK104: -0.044451181 | XEL104: =VARP(Optimization!$XEK$81:$XEK$89) -> 0.31847453 | XEM104: 0.03328048 | XEN104: -0.026524234 | XEO104: 0.0022834366 | XEP104: -0.060985533 | XEQ104: 0.0017012463 | XER104: -0.00070856381 | XES104: 0.0040489905 | XET104: -0.0029539931
XDZ105: Column 13 | XEA105: -0.00043980075 | XEB105: 0.00028828677 | XEC105: 0.055901842 | XED105: -0.020781048 | XEE105: 0.035635431 | XEF105: -0.0051217112 | XEG105: 0.0076903936 | XEH105: 0.04787861 | XEI105: -0.0066987905 | XEJ105: 0.07946659 | XEK105: -0.030255137 | XEL105: 0.03328048 | XEM105: =VARP(Optimization!$XEL$81:$XEL$89) -> 0.28395871 | XEN105: -0.014275701 | XEO105: 0.018324362 | XEP105: -0.044884852 | XEQ105: 0.032251641 | XER105: 0.019018293 | XES105: 0.0027201235 | XET105: -0.0049768775
XDZ106: Column 14 | XEA106: 0.0067909854 | XEB106: 0.01134648 | XEC106: -0.035901196 | XED106: 0.025344648 | XEE106: 0.0023765658 | XEF106: 0.0093659131 | XEG106: 0.0043661656 | XEH106: -0.012509141 | XEI106: 0.006540841 | XEJ106: -0.010245535 | XEK106: 0.023151808 | XEL106: -0.026524234 | XEM106: -0.014275701 | XEN106: =VARP(Optimization!$XEM$81:$XEM$89) -> 0.046098859 | XEO106: 0.0012013039 | XEP106: 0.025060496 | XEQ106: 0.008803533 | XER106: 0.023746981 | XES106: 0.015834413 | XET106: 0.0036451752
XDZ107: Column 15 | XEA107: 0.0069238614 | XEB107: 0.0068607378 | XEC107: 0.08471569 | XED107: 0.011008952 | XEE107: 0.0090556505 | XEF107: -0.011021972 | XEG107: -0.0025307651 | XEH107: 0.012905638 | XEI107: 0.010972326 | XEJ107: 0.0043889327 | XEK107: 0.0090693778 | XEL107: 0.0022834366 | XEM107: 0.018324362 | XEN107: 0.0012013039 | XEO107: =VARP(Optimization!$XEN$81:$XEN$89) -> 0.041644442 | XEP107: 0.006797448 | XEQ107: 0.0086037887 | XER107: 0.00025843336 | XES107: -0.011808583 | XET107: -0.00350569
XDZ108: Column 16 | XEA108: -0.0047378143 | XEB108: 0.0010779279 | XEC108: -0.087771249 | XED108: 0.016730136 | XEE108: -0.0051612985 | XEF108: 0.01419749 | XEG108: -0.010929633 | XEH108: -0.050446595 | XEI108: -0.0099782444 | XEJ108: -0.039580919 | XEK108: 0.048387648 | XEL108: -0.060985533 | XEM108: -0.044884852 | XEN108: 0.025060496 | XEO108: 0.006797448 | XEP108: =VARP(Optimization!$XEO$81:$XEO$89) -> 0.067485224 | XEQ108: -0.0030777465 | XER108: -0.0031814428 | XES108: 0.0029216526 | XET108: 0.0018117701
XDZ109: Column 17 | XEA109: 0.012047011 | XEB109: 0.0094057848 | XEC109: 0.038660723 | XED109: 0.018910592 | XEE109: 0.0052390247 | XEF109: -0.0034993484 | XEG109: 0.0055712843 | XEH109: 0.023639476 | XEI109: 0.022515837 | XEJ109: 0.027889737 | XEK109: -0.0010832545 | XEL109: 0.0017012463 | XEM109: 0.032251641 | XEN109: 0.008803533 | XEO109: 0.0086037887 | XEP109: -0.0030777465 | XEQ109: =VARP(Optimization!$XEP$81:$XEP$89) -> 0.021772266 | XER109: 0.014652848 | XES109: 0.0077399204 | XET109: 0.00088314386
XDZ110: Column 18 | XEA110: 0.0096288346 | XEB110: 0.010888802 | XEC110: 0.005320121 | XED110: 0.01993609 | XEE110: 0.0046324304 | XEF110: 0.0024535247 | XEG110: 0.0091253375 | XEH110: 0.018675044 | XEI110: 0.015491637 | XEJ110: 0.019612461 | XEK110: 0.0015242988 | XEL110: -0.00070856381 | XEM110: 0.019018293 | XEN110: 0.023746981 | XEO110: 0.00025843336 | XEP110: -0.0031814428 | XEQ110: 0.014652848 | XER110: =VARP(Optimization!$XEQ$81:$XEQ$89) -> 0.022682318 | XES110: 0.010507032 | XET110: 0.0026453401
XDZ111: Column 19 | XEA111: 0.0034553939 | XEB111: 0.0010892993 | XEC111: -0.013390588 | XED111: 0.013011205 | XEE111: 0.0046282722 | XEF111: 0.017522646 | XEG111: 0.0047058735 | XEH111: -0.0098297076 | XEI111: 0.00601505 | XEJ111: -0.001771877 | XEK111: 0.0035811228 | XEL111: 0.0040489905 | XEM111: 0.0027201235 | XEN111: 0.015834413 | XEO111: -0.011808583 | XEP111: 0.0029216526 | XEQ111: 0.0077399204 | XER111: 0.010507032 | XES111: =VARP(Optimization!$XER$81:$XER$89) -> 0.022327202 | XET111: 0.0083806339
XDZ112: Column 20 | XEA112: 0.0012340001 | XEB112: 0.00024879583 | XEC112: -0.0011733514 | XED112: 0.0086489277 | XEE112: 0.0031366947 | XEF112: 0.010570992 | XEG112: 0.0018618656 | XEH112: -0.0026375617 | XEI112: 0.0032552748 | XEJ112: -0.0029370354 | XEK112: 0.0029411956 | XEL112: -0.0029539931 | XEM112: -0.0049768775 | XEN112: 0.0036451752 | XEO112: -0.00350569 | XEP112: 0.0018117701 | XEQ112: 0.00088314386 | XER112: 0.0026453401 | XES112: 0.0083806339 | XET112: =VARP(Optimization!$XES$81:$XES$89) -> 0.0059043472

Sheet Data & Analysis
W2: =substitute(cell,char(160),"")
D3: Raw Adj. Prices, ending on Jan. 1 of following year | P3: Raw Div. Payouts, starting Jan. 1 and ending Dec. 31 | AB3: Adj.Prices + Div. Payouts, starting and ending on Jan 1. of following year | BK3: Dividend Growth (O), Monthly | BR3: Dividend Growth (O), Quarterly | BW3: Dividend Growth (O), Yearly
E4: 2016 | F4: 2017 | G4: =F4+1 -> 2018 | H4: =G4+1 -> 2019 | I4: =H4+1 -> 2020 | J4: =I4+1 -> 2021 | K4: =J4+1 -> 2022 | L4: =K4+1 -> 2023 | M4: =L4+1 -> 2024 | N4: =M4+1 -> 2025 | Q4: 2016 | R4: 2017 | S4: =R4+1 -> 2018 | T4: =S4+1 -> 2019 | U4: =T4+1 -> 2020 | V4: =U4+1 -> 2021 | W4: =V4+1 -> 2022 | X4: =W4+1 -> 2023 | Y4: =X4+1 -> 2024 | Z4: =Y4+1 -> 2025 | AC4: 2017 | AD4: =AC4+1 -> 2018 | AE4: =AD4+1 -> 2019 | AF4: =AE4+1 -> 2020 | AG4: =AF4+1 -> 2021 | AH4: =AG4+1 -> 2022 | AI4: =AH4+1 -> 2023 | AJ4: =AI4+1 -> 2024 | AK4: 2025, e | AL4: mean | AM4: mean w/o 25 | AP4: {=TRANSPOSE(AB5:AB24)} -> VOO | AQ4: DIA | AR4: TSLA | AS4: BAC | AT4: SBUX | AU4: O | AV4: VZ | AW4: AMZN | AX4: GOOGL | AY4: CRM | AZ4: CVX | BA4: AMD | BB4: LULU | BC4: LMT | BD4: UPS | BE4: XOM | BF4: COST | BG4: V | BH4: SO | BI4: DUK | BK4: Date | BL4: Div Payout | BM4: % MoM G | BN4: Pattern | BO4: Ticket | BR4: Qtr | BS4: QoQ % G | BW4: Yr | BX4: Yr Div | BY4: YoY % G | CJ4: SPG
C5: #VALUE! | D5: VOO | E5: 180.64 | F5: 228.19 | G5: 222.74 | H5: 271.03 | I5: 317.54 | J5: 391.54 | K5: 359.36 | L5: 433.96 | M5: 548.15 | N5: {=_FV(C5,"Price")} -> 680.95 | P5: VOO | Q5: 4.138 | R5: 4.368 | S5: 4.737 | T5: 5.571 | U5: 5.303 | V5: 5.437 | W5: 5.947 | X5: 6.357 | Y5: =SUM(1.739, 1.639,1.784,1.543) -> 6.705 | Z5: 5.297 | AB5: VOO | AC5: =LN((F5+R5)/E5) -> 0.25263356 | AD5: =LN((G5+S5)/F5) -> -0.0031294809 | AE5: =LN((H5+T5)/G5) -> 0.21657086 | AF5: =LN((I5+U5)/H5) -> 0.17493662 | AG5: =LN((J5+V5)/I5) -> 0.22327455 | AH5: =LN((K5+W5)/J5) -> -0.069349585 | AI5: =LN((L5+X5)/K5) -> 0.20317025 | AJ5: =LN((M5+Y5)/L5) -> 0.24575445 | AK5: =LN((N5+(Y5*(1+Z26)))/M5) -> 0.22730931 | AL5: =AVERAGE(AC5:AK5) -> 0.16346339 | AM5: =AVERAGE(AC5:AJ5) -> 0.15548265 | AO5: Data w/ Dividends | AP5: {=TRANSPOSE(AL5:AL24)} -> 0.16346339 | AQ5: 0.14575541 | AR5: 0.35547289 | AS5: 0.14859534 | AT5: 0.112434 | AU5: 0.10981572 | AV5: 0.10473519 | AW5: 0.19594581 | AX5: 0.24066489 | AY5: 0.079653887 | AZ5: 0.13578023 | BA5: 0.43907858 | BB5: 0.058495927 | BC5: 0.13116359 | BD5: 0.077103487 | BE5: 0.14799551 | BF5: 0.23014475 | BG5: 0.17076746 | BH5: 0.16149093 | BI5: 0.13966844 | BJ5: 1 | BK5: 42397 | BL5: 0.192829 | BR5: Q216 | BS5: 0.0016736579 | BW5: 2016 | BX5: 2.33139 | BY5: n/a
C6: #VALUE! | D6: DIA | E6: 166.99 | F6: 225.07 | G6: 219.87 | H6: 253.89 | I6: 275.39 | J6: 327.95 | K6: 324.62 | L6: 370.49 | M6: 440.05 | N6: {=_FV(C6,"Price")} -> 521.71 | P6: DIA | Q6: 4.461 | R6: 4.875 | S6: 5.222 | T6: 5.953 | U6: 5.728 | V6: 5.742 | W6: 6.332 | X6: 6.804 | Y6: 6.831 | Z6: 5.26 | AB6: DIA | AC6: =LN((F6+R6)/E6) -> 0.31990622 | AD6: =LN((G6+S6)/F6) -> 9.7742591e-05 | AE6: =LN((H6+T6)/G6) -> 0.16704114 | AF6: =LN((I6+U6)/H6) -> 0.10187341 | AG6: =LN((J6+V6)/I6) -> 0.19203014 | AH6: =LN((K6+W6)/J6) -> 0.009112192 | AI6: =LN((L6+X6)/K6) -> 0.15036946 | AJ6: =LN((M6+Y6)/L6) -> 0.18746589 | AK6: =LN((N6+(Y6*(1+Z27)))/M6) -> 0.18390247 | AL6: =AVERAGE(AC6:AK6) -> 0.14575541 | AM6: =AVERAGE(AC6:AJ6) -> 0.14098702 | AO6: Raw Data | AP6: {=TRANSPOSE(O26:O45)} -> 0.14744253 | AQ6: 0.12657533 | AR6: 0.35547289 | AS6: 0.12636409 | AT6: 0.091041598 | AU6: 0.055574726 | AV6: 0.04128484 | AW6: 0.19594581 | AX6: 0.2401492 | AY6: 0.078012555 | AZ6: 0.087445526 | BA6: 0.43907858 | BB6: 0.058495927 | BC6: 0.10261296 | BD6: 0.034258851 | BE6: 0.097555623 | BF6: 0.21257529 | BG6: 0.16431414 | BH6: 0.11541509 | BI6: 0.094549057 | BJ6: 2 | BK6: 42426 | BL6: 0.192829 | BM6: =LN(BL6/BL5) -> 0 | BN6: =IF(BM6=0, "No Growth", "Growth") -> No Growth | BO6: =IF(BM6=0,1,2) -> 1 | BR6: Q316 | BS6: 0.0099835468 | BW6: =BW5+1 -> 2017 | BX6: 2.461236 | BY6: =LN(BX6/BX5) -> 0.054199007 | CH6: 4 | CI6: Q415 | CJ6: 42410 | CK6: 1.6 | CL6: n/a
C7: #VALUE! | D7: TSLA | E7: 16.8 | F7: 23.62 | G7: 20.47 | H7: 43.37 | I7: 264.51 | J7: 312.24 | K7: 173.22 | L7: 187.29 | M7: 404.6 | N7: {=_FV(C7,"Price")} -> 411.84 | P7: TSLA | Q7: 0 | R7: 0 | S7: 0 | T7: 0 | U7: 0 | V7: 0 | W7: 0 | X7: 0 | Y7: 0 | Z7: 0 | AB7: TSLA | AC7: =LN((F7+R7)/E7) -> 0.34071492 | AD7: =LN((G7+S7)/F7) -> -0.14313341 | AE7: =LN((H7+T7)/G7) -> 0.75080756 | AF7: =LN((I7+U7)/H7) -> 1.8081111 | AG7: =LN((J7+V7)/I7) -> 0.16589307 | AH7: =LN((K7+W7)/J7) -> -0.58920966 | AI7: =LN((L7+X7)/K7) -> 0.078095755 | AJ7: =LN((M7+Y7)/L7) -> 0.77024071 | AK7: =LN((N7+(Y7*(1+Z28)))/M7) -> 0.017736 | AL7: =AVERAGE(AC7:AK7) -> 0.35547289 | AM7: =AVERAGE(AC7:AJ7) -> 0.39769 | AO7: Difference | AP7: =AP5-AP6 -> 0.016020862 | AQ7: =AQ5-AQ6 -> 0.019180078 | AR7: =AR5-AR6 -> 0 | AS7: =AS5-AS6 -> 0.022231257 | AT7: =AT5-AT6 -> 0.021392398 | AU7: =AU5-AU6 -> 0.054240993 | AV7: =AV5-AV6 -> 0.063450346 | AW7: =AW5-AW6 -> 0 | ... BI7: =BI5-BI6 -> 0.045119384 | BJ7: 3 | BK7: 42459 | BL7: 0.192829 | BM7: =LN(BL7/BL6) -> 0 | BN7: =IF(BM7=0, "No Growth", "Growth") -> No Growth | BO7: =IF(BM7=0,1,2) -> 1 | BR7: Q416 | BS7: 0.0049546438 | BW7: =BW6+1 -> 2018 | BX7: 2.560074 | BY7: =LN(BX7/BX6) -> 0.039372502 | CH7: 1 | CI7: Q116 | CJ7: 42503 | CK7: 1.6 | CL7: =LN(CK7/CK6) -> 0 | CM7: =IF(CL7<=0, "No Growth", "Growth") -> No Growth
C8: #VALUE! | D8: BAC | E8: 18.56 | F8: 26.65 | G8: 24.15 | H8: 28.48 | I8: 26.41 | J8: 41.89 | K8: 32.97 | L8: 32.58 | M8: 45.49 | N8: {=_FV(C8,"Price")} -> 57.875 | P8: BAC | Q8: 0.25 | R8: 0.39 | S8: 0.54 | T8: 0.66 | U8: 0.72 | V8: 0.78 | W8: 0.86 | X8: 0.92 | Y8: =SUM((0.26*2),(0.24*2)) -> 1 | Z8: 0.8 | AB8: BAC | AC8: =LN((F8+R8)/E8) -> 0.37630852 | AD8: =LN((G8+S8)/F8) -> -0.076390847 | AE8: =LN((H8+T8)/G8) -> 0.18782742 | AF8: =LN((I8+U8)/H8) -> -0.04856196 | AG8: =LN((J8+V8)/I8) -> 0.47975337 | AH8: =LN((K8+W8)/J8) -> -0.21369915 | AI8: =LN((L8+X8)/K8) -> 0.015947382 | AJ8: =LN((M8+Y8)/L8) -> 0.35553863 | AK8: =LN((N8+(Y8*(1+Z29)))/M8) -> 0.26063473 | AL8: =AVERAGE(AC8:AK8) -> 0.14859534 | AM8: =AVERAGE(AC8:AJ8) -> 0.13459042 | BJ8: 4 | BK8: 42488 | BL8: 0.192829 | BM8: =LN(BL8/BL7) -> 0 | BN8: =IF(BM8=0, "No Growth", "Growth") -> No Growth | BO8: =IF(BM8=0,1,2) -> 1 | BR8: Q117 | BS8: 0.04194205 | BW8: =BW7+1 -> 2019 | BX8: 2.635656 | BY8: =LN(BX8/BX7) -> 0.029095943 | CH8: 2 | CI8: Q216 | CJ8: 42597 | CK8: 1.65 | CL8: =LN(CK8/CK7) -> 0.030771659 | CM8: =IF(CL8<=0, "No Growth", "Growth") -> Growth
C9: #VALUE! | D9: SBUX | E9: 45.86 | F9: 48.06 | G9: 58.98 | H9: 74.8 | I9: 87.13 | J9: 89.95 | K9: 102.22 | L9: 88.96 | M9: 105.65 | N9: {=_FV(C9,"Price")} -> 104.06 | P9: SBUX | Q9: 0.85 | R9: 1.05 | S9: 1.32 | T9: 1.49 | U9: 1.68 | V9: 1.84 | W9: 2 | X9: 2.16 | Y9: 2.32 | Z9: 1.83 | AB9: SBUX | AC9: =LN((F9+R9)/E9) -> 0.068469403 | AD9: =LN((G9+S9)/F9) -> 0.22688187 | AE9: =LN((H9+T9)/G9) -> 0.25734346 | AF9: =LN((I9+U9)/H9) -> 0.17168137 | AG9: =LN((J9+V9)/I9) -> 0.052102103 | AH9: =LN((K9+W9)/J9) -> 0.14725009 | AI9: =LN((L9+X9)/K9) -> -0.11495003 | AJ9: =LN((M9+Y9)/L9) -> 0.19366658 | AK9: =LN((N9+(Y9*(1+Z30)))/M9) -> 0.0094611099 | AL9: =AVERAGE(AC9:AK9) -> 0.112434 | AM9: =AVERAGE(AC9:AJ9) -> 0.12530561 | BJ9: 5 | BK9: 42517 | BL9: 0.192829 | BM9: =LN(BL9/BL8) -> 0 | BN9: =IF(BM9=0, "No Growth", "Growth") -> No Growth | BO9: =IF(BM9=0,1,2) -> 1 | BR9: Q217 | BS9: 0.0015785477 | BW9: =BW8+1 -> 2020 | BX9: 2.717052 | BY9: =LN(BX9/BX8) -> 0.030415362 | CH9: 3 | CI9: Q316 | CJ9: 42688 | CK9: 1.65 | CL9: =LN(CK9/CK8) -> 0 | CM9: =IF(CL9<=0, "No Growth", "Growth") -> No Growth
C10: #VALUE! | D10: O | E10: 38.22 | F10: 35.63 | G10: 48.26 | H10: 57.2 | I10: 45.11 | J10: 57.07 | K10: 58.31 | L10: 49.3 | M10: 52.13 | N10: {=_FV(C10,"Price")} -> 63.025 | P10: O | Q10: 2.33139 | R10: 2.46124 | S10: 2.56007 | T10: 2.63566 | U10: 2.71705 | V10: 2.77498 | W10: 2.972 | X10: 3.062 | Y10: 3.136 | Z10: 2.68 | AB10: O | AC10: =LN((F10+R10)/E10) -> -0.0033746044 | AD10: =LN((G10+S10)/F10) -> 0.35510338 | AE10: =LN((H10+T10)/G10) -> 0.21499874 | AF10: =LN((I10+U10)/H10) -> -0.17896252 | AG10: =LN((J10+V10)/I10) -> 0.2826536 | AH10: =LN((K10+W10)/J10) -> 0.071207577 | AI10: =LN((L10+X10)/K10) -> -0.10759247 | AJ10: =LN((M10+Y10)/L10) -> 0.11423381 | AK10: =LN((N10+(Y10*(1+Z31)))/M10) -> 0.24007396 | AL10: =AVERAGE(AC10:AK10) -> 0.10981572 | AM10: =AVERAGE(AC10:AJ10) -> 0.09353344 | BJ10: 6 | BK10: 42550 | BL10: 0.193798 | BM10: =LN(BL10/BL9) -> 0.0050125937 | BN10: =IF(BM10=0, "No Growth", "Growth") -> Growth | BO10: =IF(BM10=0,1,2) -> 2 | BR10: Q317 | BS10: 0.0031496396 | BU10: Mean | BV10: =AVERAGE(BS5:BS42) -> 0.0087280229 | BW10: =BW9+1 -> 2021 | BX10: 2.774975 | BY10: =LN(BX10/BX9) -> 0.021094269 | CH10: 4 | CI10: Q416 | CJ10: 42776 | CK10: 1.75 | CL10: =LN(CK10/CK9) -> 0.0588405 | CM10: =IF(CL10<=0, "No Growth", "Growth") -> Growth
C11: #VALUE! | D11: VZ | E11: 30.4 | F11: 35.16 | G11: 37.51 | H11: 42.21 | I11: 40.58 | J11: 41.24 | K11: 33.97 | L11: 37.15 | M11: 36.85 | N11: {=_FV(C11,"Price")} -> 44.08 | P11: VZ | Q11: 2.273 | R11: 2.324 | S11: 2.373 | T11: 2.424 | U11: 2.473 | V11: 2.524 | W11: 2.573 | X11: 2.624 | Y11: 2.673 | Z11: 2.724 | AB11: VZ | AC11: =LN((F11+R11)/E11) -> 0.20947157 | AD11: =LN((G11+S11)/F11) -> 0.1260411 | AE11: =LN((H11+T11)/G11) -> 0.17388834 | AF11: =LN((I11+U11)/H11) -> 0.019774755 | AG11: =LN((J11+V11)/I11) -> 0.075536227 | AH11: =LN((K11+W11)/J11) -> -0.12091901 | AI11: =LN((L11+X11)/K11) -> 0.15773565 | AJ11: =LN((M11+Y11)/L11) -> 0.06191901 | AK11: =LN((N11+(Y11*(1+Z32)))/M11) -> 0.23916904 | AL11: =AVERAGE(AC11:AK11) -> 0.10473519 | AM11: =AVERAGE(AC11:AJ11) -> 0.087930954 | BJ11: 7 | BK11: 42579 | BL11: 0.193798 | BM11: =LN(BL11/BL10) -> 0 | BN11: =IF(BM11=0, "No Growth", "Growth") -> No Growth | BO11: =IF(BM11=0,1,2) -> 1 | BR11: Q417 | BS11: 0.0015711075 | BU11: Stdev | BV11: =_xlfn.STDEV.S(BS5:BS42) -> 0.012164492 | BW11: =BW10+1 -> 2022 | BX11: 2.972 | BY11: =LN(BX11/BX10) -> 0.068593389 | CH11: 1 | CI11: Q117 | CJ11: 42870 | CK11: 1.75 | CL11: =LN(CK11/CK10) -> 0 | CM11: =IF(CL11<=0, "No Growth", "Growth") -> No Growth
C12: #VALUE! | D12: AMZN | E12: 41.17 | F12: 72.54 | G12: 85.94 | H12: 100.44 | I12: 160.31 | J12: 149.57 | K12: 103.13 | L12: 155.2 | M12: 237.68 | N12: {=_FV(C12,"Price")} -> 240.14 | P12: AMZN | Q12: 0 | R12: 0 | S12: 0 | T12: 0 | U12: 0 | V12: 0 | W12: 0 | X12: 0 | Y12: 0 | Z12: 0 | AB12: AMZN | AC12: =LN((F12+R12)/E12) -> 0.5664283 | AD12: =LN((G12+S12)/F12) -> 0.16951124 | AE12: =LN((H12+T12)/G12) -> 0.15591116 | AF12: =LN((I12+U12)/H12) -> 0.46754891 | AG12: =LN((J12+V12)/I12) -> -0.06934493 | AH12: =LN((K12+W12)/J12) -> -0.37177418 | AI12: =LN((L12+X12)/K12) -> 0.40872428 | AJ12: =LN((M12+Y12)/L12) -> 0.42621062 | AK12: =LN((N12+(Y12*(1+Z33)))/M12) -> 0.010296855 | AL12: =AVERAGE(AC12:AK12) -> 0.19594581 | AM12: =AVERAGE(AC12:AJ12) -> 0.21915192 | BJ12: 8 | BK12: 42612 | BL12: 0.195736 | BM12: =LN(BL12/BL11) -> 0.009950433 | BN12: =IF(BM12=0, "No Growth", "Growth") -> Growth | BO12: =IF(BM12=0,1,2) -> 2 | BR12: Q118 | BS12: 0.032435586 | BW12: =BW11+1 -> 2023 | BX12: 3.062 | BY12: =LN(BX12/BX11) -> 0.02983317 | CH12: 2 | CI12: Q217 | CJ12: 42962 | CK12: 1.8 | CL12: =LN(CK12/CK11) -> 0.028170877 | CM12: =IF(CL12<=0, "No Growth", "Growth") -> Growth
C13: #VALUE! | D13: GOOGL | E13: 40.73 | F13: 58.71 | G13: 55.91 | H13: 71.15 | I13: 90.74 | J13: 134.38 | K13: 98.16 | L13: 139.14 | M13: 203.36 | N13: {=_FV(C13,"Price")} -> 353.65 | P13: GOOGL | Q13: 0 | R13: 0 | S13: 0 | T13: 0 | U13: 0 | V13: 0 | W13: 0 | X13: 0 | Y13: 0.6 | Z13: 0.62 | AB13: GOOGL | AC13: =LN((F13+R13)/E13) -> 0.36564515 | AD13: =LN((G13+S13)/F13) -> -0.048866815 | AE13: =LN((H13+T13)/G13) -> 0.24104707 | AF13: =LN((I13+U13)/H13) -> 0.24320795 | AG13: =LN((J13+V13)/I13) -> 0.39267333 | AH13: =LN((K13+W13)/J13) -> -0.31407281 | AI13: =LN((L13+X13)/K13) -> 0.34888182 | AJ13: =LN((M13+Y13)/L13) -> 0.38244328 | AK13: =LN((N13+(Y13*(1+Z34)))/M13) -> 0.55502507 | AL13: =AVERAGE(AC13:AK13) -> 0.24066489 | AM13: =AVERAGE(AC13:AJ13) -> 0.20136987 | BJ13: 9 | BK13: 42642 | BL13: 0.195736 | BM13: =LN(BL13/BL12) -> 0 | BN13: =IF(BM13=0, "No Growth", "Growth") -> No Growth | BO13: =IF(BM13=0,1,2) -> 1 | BR13: Q218 | BS13: 0.0030349322 | BW13: =BW12+1 -> 2024 | BX13: 3.136 | BY13: =LN(BX13/BX12) -> 0.023879805 | CH13: 3 | CI13: Q317 | CJ13: 43054 | CK13: 1.85 | CL13: =LN(CK13/CK12) -> 0.027398974 | CM13: =IF(CL13<=0, "No Growth", "Growth") -> Growth
C14: #VALUE! | D14: CRM | E14: 78.28 | F14: 112.72 | G14: 150.39 | H14: 180.41 | I14: 223.21 | J14: 230.21 | K14: 166.22 | L14: 278.16 | M14: 340.03 | N14: {=_FV(C14,"Price")} -> 157.97 | P14: CRM | Q14: 0 | R14: 0 | S14: 0 | T14: 0 | U14: 0 | V14: 0 | W14: 0 | X14: 0 | Y14: 1.6 | Z14: 1.248 | AB14: CRM | AC14: =LN((F14+R14)/E14) -> 0.36461473 | AD14: =LN((G14+S14)/F14) -> 0.28832505 | AE14: =LN((H14+T14)/G14) -> 0.18200012 | AF14: =LN((I14+U14)/H14) -> 0.21288099 | AG14: =LN((J14+V14)/I14) -> 0.030878903 | AH14: =LN((K14+W14)/J14) -> -0.32567972 | AI14: =LN((L14+X14)/K14) -> 0.51488428 | AJ14: =LN((M14+Y14)/L14) -> 0.20553179 | AK14: =LN((N14+(Y14*(1+Z35)))/M14) -> -0.75655115 | AL14: =AVERAGE(AC14:AK14) -> 0.079653887 | AM14: =AVERAGE(AC14:AJ14) -> 0.18417952 | BJ14: 10 | BK14: 42671 | BL14: 0.195736 | BM14: =LN(BL14/BL13) -> 0 | BN14: =IF(BM14=0, "No Growth", "Growth") -> No Growth | BO14: =IF(BM14=0,1,2) -> 1 | BR14: Q318 | BS14: 0.001514019 | BX14: Mean | BY14: =AVERAGE(BY6:BY13) -> 0.037060431 | CH14: 4 | CI14: Q417 | CJ14: 43144 | CK14: 1.95 | CL14: =LN(CK14/CK13) -> 0.052643733 | CM14: =IF(CL14<=0, "No Growth", "Growth") -> Growth
C15: #VALUE! | D15: CVX | E15: 76.67 | F15: 89.74 | G15: 85.25 | H15: 82.9 | I15: 69.66 | J15: 113 | K15: 155.13 | L15: 136.59 | M15: 144.17 | N15: {=_FV(C15,"Price")} -> 168.43 | P15: CVX | Q15: 4.29 | R15: 4.32 | S15: 4.48 | T15: 4.76 | U15: 5.16 | V15: 5.31 | W15: 5.68 | X15: 6.04 | Y15: 6.52 | Z15: 5.13 | AB15: CVX | AC15: =LN((F15+R15)/E15) -> 0.20442238 | AD15: =LN((G15+S15)/F15) -> -0.00011143924 | AE15: =LN((H15+T15)/G15) -> 0.027877579 | AF15: =LN((I15+U15)/H15) -> -0.10254983 | AG15: =LN((J15+V15)/I15) -> 0.52968203 | AH15: =LN((K15+W15)/J15) -> 0.35283573 | AI15: =LN((L15+X15)/K15) -> -0.084009611 | AJ15: =LN((M15+Y15)/L15) -> 0.098241008 | AK15: =LN((N15+(Y15*(1+Z36)))/M15) -> 0.19563423 | AL15: =AVERAGE(AC15:AK15) -> 0.13578023 | AM15: =AVERAGE(AC15:AJ15) -> 0.12829848 | BJ15: 11 | BK15: 42703 | BL15: 0.195736 | BM15: =LN(BL15/BL14) -> 0 | BN15: =IF(BM15=0, "No Growth", "Growth") -> No Growth | BO15: =IF(BM15=0,1,2) -> 1 | BR15: Q418 | BS15: 0.0030211786 | BX15: St dev | BY15: =_xlfn.STDEV.S(BY6:BY13) -> 0.016396317 | CH15: 1 | CI15: Q118 | CJ15: 43236 | CK15: 1.95 | CL15: =LN(CK15/CK14) -> 0 | CM15: =IF(CL15<=0, "No Growth", "Growth") -> No Growth
C16: #VALUE! | D16: AMD | E16: 10.37 | F16: 13.74 | G16: 24.41 | H16: 47 | I16: 85.64 | J16: 114.25 | K16: 75.15 | L16: 167.69 | M16: 115.95 | N16: {=_FV(C16,"Price")} -> 539.49 | P16: AMD | Q16: 0 | R16: 0 | S16: 0 | T16: 0 | U16: 0 | V16: 0 | W16: 0 | X16: 0 | Y16: 0 | Z16: 0 | AB16: AMD | AC16: =LN((F16+R16)/E16) -> 0.28139426 | AD16: =LN((G16+S16)/F16) -> 0.5746816 | AE16: =LN((H16+T16)/G16) -> 0.65515472 | AF16: =LN((I16+U16)/H16) -> 0.60000486 | AG16: =LN((J16+V16)/I16) -> 0.28823657 | AH16: =LN((K16+W16)/J16) -> -0.41890291 | AI16: =LN((L16+X16)/K16) -> 0.80263092 | AJ16: =LN((M16+Y16)/L16) -> -0.36895797 | AK16: =LN((N16+(Y16*(1+Z37)))/M16) -> 1.5374652 | AL16: =AVERAGE(AC16:AK16) -> 0.43907858 | AM16: =AVERAGE(AC16:AJ16) -> 0.30178026 | BJ16: 12 | BK16: 42733 | BL16: 0.196705 | BM16: =LN(BL16/BL15) -> 0.004938332 | BN16: =IF(BM16=0, "No Growth", "Growth") -> Growth | BO16: =IF(BM16=0,1,2) -> 2 | BR16: Q119 | BS16: 0.022372504 | CH16: 2 | CI16: Q218 | CJ16: 43328 | CK16: 2 | CL16: =LN(CK16/CK15) -> 0.025317808 | CM16: =IF(CL16<=0, "No Growth", "Growth") -> Growth | CS16: Total % | CT16: Total Events, increased | CU16: Total Events, decreased | CV16: Total Qtr(s) | CW16: % chance of increase | CX16: % change of decrease
C17: #VALUE! | D17: LULU | E17: 67.51 | F17: 78.21 | G17: 147.81 | H17: 239.39 | I17: 328.68 | J17: 333.76 | K17: 306.88 | L17: 453.82 | M17: 414.2 | N17: {=_FV(C17,"Price")} -> 114.29 | P17: LULU | Q17: 0 | R17: 0 | S17: 0 | T17: 0 | U17: 0 | V17: 0 | W17: 0 | X17: 0 | Y17: 0 | Z17: 0 | AB17: LULU | AC17: =LN((F17+R17)/E17) -> 0.14712178 | AD17: =LN((G17+S17)/F17) -> 0.63653015 | AE17: =LN((H17+T17)/G17) -> 0.48216636 | AF17: =LN((I17+U17)/H17) -> 0.31699061 | AG17: =LN((J17+V17)/I17) -> 0.015337539 | AH17: =LN((K17+W17)/J17) -> -0.08396538 | AI17: =LN((L17+X17)/K17) -> 0.39124385 | AJ17: =LN((M17+Y17)/L17) -> -0.091351695 | AK17: =LN((N17+(Y17*(1+Z38)))/M17) -> -1.2876099 | AL17: =AVERAGE(AC17:AK17) -> 0.058495927 | AM17: =AVERAGE(AC17:AJ17) -> 0.22675915 | BJ17: 1 | BK17: 42765 | BL17: 0.204457 | BM17: =LN(BL17/BL16) -> 0.03865254 | BN17: =IF(BM17=0, "No Growth", "Growth") -> Growth | BO17: =IF(BM17=0,1,2) -> 2 | BR17: Q219 | BS17: 0.0014738531 | CH17: 3 | CI17: Q318 | CJ17: 43419 | CK17: 2 | CL17: =LN(CK17/CK16) -> 0 | CM17: =IF(CL17<=0, "No Growth", "Growth") -> No Growth | CR17: Q4 increases | CS17: =SUMIF(CH7:CH44, "4", CL7:CL44) -> 0.16215233 | CT17: =COUNTIFS(CH7:CH44, "4", CM7:CM44, "Growth") -> 4 | CU17: =COUNTIFS(CH7:CH44, "4", CM7:CM44, "No Growth") -> 5 | CV17: =SUM(CT17:CU17) -> 9 | CW17: =CT17/$CV17 -> 0.44444444 | CX17: =CU17/$CV17 -> 0.55555556
C18: #VALUE! | D18: LMT | E18: 199.39 | F18: 288.78 | G18: 241.81 | H18: 366.58 | I18: 282.64 | J18: 352.1 | K18: 430.18 | L18: 409.56 | M18: 453.11 | N18: {=_FV(C18,"Price")} -> 502.09 | P18: LMT | Q18: 6.77 | R18: 7.46 | S18: 8.2 | T18: 9 | U18: 9.8 | V18: 10.6 | W18: 11.4 | X18: 12.15 | Y18: 12.75 | Z18: 9.9 | AB18: LMT | AC18: =LN((F18+R18)/E18) -> 0.39590723 | AD18: =LN((G18+S18)/F18) -> -0.14416424 | AE18: =LN((H18+T18)/G18) -> 0.4403192 | AF18: =LN((I18+U18)/H18) -> -0.22595726 | AG18: =LN((J18+V18)/I18) -> 0.24940204 | AH18: =LN((K18+W18)/J18) -> 0.22644398 | AI18: =LN((L18+X18)/K18) -> -0.019885852 | AJ18: =LN((M18+Y18)/L18) -> 0.12880175 | AK18: =LN((N18+(Y18*(1+Z39)))/M18) -> 0.12960543 | AL18: =AVERAGE(AC18:AK18) -> 0.13116359 | AM18: =AVERAGE(AC18:AJ18) -> 0.13135836 | BJ18: 2 | BK18: 42793 | BL18: 0.204457 | BM18: =LN(BL18/BL17) -> 0 | BN18: =IF(BM18=0, "No Growth", "Growth") -> No Growth | BO18: =IF(BM18=0,1,2) -> 1 | BR18: Q319 | BS18: 0.0029412054 | CH18: 4 | CI18: Q418 | CJ18: 43509 | CK18: 2.05 | CL18: =LN(CK18/CK17) -> 0.024692613 | CM18: =IF(CL18<=0, "No Growth", "Growth") -> Growth | CR18: Q3 increases | CS18: =SUMIF(CH7:CH44, "3", CL7:CL44) -> 0.17497758 | CT18: =COUNTIFS(CH7:CH44, "3", CM7:CM44, "Growth") -> 4 | CU18: =COUNTIFS(CH7:CH44, "3", CM7:CM44, "No Growth") -> 5 | CV18: =SUM(CT18:CU18) -> 9 | CW18: =CT18/$CV18 -> 0.44444444 | CX18: =CU18/$CV18 -> 0.55555556
C19: #VALUE! | D19: UPS | E19: 79.33 | F19: 95.41 | G19: 81.56 | H19: 82.82 | I19: 128.28 | J19: 170.96 | K19: 161.78 | L19: 128.87 | M19: 108.74 | N19: {=_FV(C19,"Price")} -> 107.98 | P19: UPS | Q19: 3.12 | R19: 3.32 | S19: 3.64 | T19: 3.84 | U19: 4.04 | V19: 4.08 | W19: 6.08 | X19: 6.48 | Y19: 6.52 | Z19: 4.92 | AB19: UPS | AC19: =LN((F19+R19)/E19) -> 0.21877248 | AD19: =LN((G19+S19)/F19) -> -0.11318196 | AE19: =LN((H19+T19)/G19) -> 0.060653471 | AF19: =LN((I19+U19)/H19) -> 0.46855365 | AG19: =LN((J19+V19)/I19) -> 0.31079914 | AH19: =LN((K19+W19)/J19) -> -0.018299312 | AI19: =LN((L19+X19)/K19) -> -0.17837337 | AJ19: =LN((M19+Y19)/L19) -> -0.1116137 | AK19: =LN((N19+(Y19*(1+Z40)))/M19) -> 0.056620972 | AL19: =AVERAGE(AC19:AK19) -> 0.077103487 | AM19: =AVERAGE(AC19:AJ19) -> 0.079663801 | BJ19: 3 | BK19: 42824 | BL19: 0.204457 | BM19: =LN(BL19/BL18) -> 0 | BN19: =IF(BM19=0, "No Growth", "Growth") -> No Growth | BO19: =IF(BM19=0,1,2) -> 1 | BR19: Q419 | BS19: 0.001467365 | CH19: 1 | CI19: Q119 | CJ19: 43601 | CK19: 2.05 | CL19: =LN(CK19/CK18) -> 0 | CM19: =IF(CL19<=0, "No Growth", "Growth") -> No Growth | CR19: Q2 increases | CS19: =SUMIF(CH7:CH44, "2", CL7:CL44) -> 0.28122966 | CT19: =COUNTIFS(CH7:CH44, "2", CM7:CM44, "Growth") -> 9 | CU19: =COUNTIFS(CH7:CH44, "2", CM7:CM44, "No Growth") -> 1 | CV19: =SUM(CT19:CU19) -> 10 | CW19: =CT19/$CV19 -> 0.9 | CX19: =CU19/$CV19 -> 0.1
C20: #VALUE! | D20: XOM | E20: 56.54 | F20: 61.07 | G20: 53.39 | H20: 47.43 | I20: 36.97 | J20: 66.48 | K20: 105.55 | L20: 96.74 | M20: 103.95 | N20: {=_FV(C20,"Price")} -> 136.04 | P20: XOM | Q20: 2.98 | R20: 3.06 | S20: 3.23 | T20: 3.43 | U20: 3.48 | V20: 3.49 | W20: 3.55 | X20: 3.68 | Y20: 3.84 | Z20: 2.97 | AB20: XOM | AC20: =LN((F20+R20)/E20) -> 0.12596392 | AD20: =LN((G20+S20)/F20) -> -0.075658468 | AE20: =LN((H20+T20)/G20) -> -0.048546703 | AF20: =LN((I20+U20)/H20) -> -0.1591883 | AG20: =LN((J20+V20)/I20) -> 0.63795981 | AH20: =LN((K20+W20)/J20) -> 0.49536374 | AI20: =LN((L20+X20)/K20) -> -0.049823384 | AJ20: =LN((M20+Y20)/L20) -> 0.10815792 | AK20: =LN((N20+(Y20*(1+Z41)))/M20) -> 0.29773109 | AL20: =AVERAGE(AC20:AK20) -> 0.14799551 | AM20: =AVERAGE(AC20:AJ20) -> 0.12927857 | BJ20: 4 | BK20: 42852 | BL20: 0.204457 | BM20: =LN(BL20/BL19) -> 0 | BN20: =IF(BM20=0, "No Growth", "Growth") -> No Growth | BO20: =IF(BM20=0,1,2) -> 1 | BR20: Q120 | BS20: 0.024621305 | CH20: 2 | CI20: Q219 | CJ20: 43692 | CK20: 2.1 | CL20: =LN(CK20/CK19) -> 0.024097552 | CM20: =IF(CL20<=0, "No Growth", "Growth") -> Growth | CR20: Q1 increases | CS20: =SUMIF(CH7:CH44, "1", CL7:CL44) -> -0.32289536 | CT20: =COUNTIFS(CH7:CH44, "1", CM7:CM44, "Growth") -> 4 | CU20: =COUNTIFS(CH7:CH44, "1", CM7:CM44, "No Growth") -> 6 | CV20: =SUM(CT20:CU20) -> 10 | CW20: =CT20/$CV20 -> 0.4 | CX20: =CU20/$CV20 -> 0.6
C21: #VALUE! | D21: COST | E21: 139.74 | F21: 174.84 | G21: 194.59 | H21: 279.72 | I21: 333.93 | J21: 482.27 | K21: 491.27 | L21: 688.23 | M21: 976.17 | N21: {=_FV(C21,"Price")} -> 946.68 | P21: COST | Q21: 1.75 | R21: 8.95 | S21: 2.21 | T21: 2.52 | U21: 12.75 | V21: 3.07 | W21: 3.49 | X21: 18.96 | Y21: 4.5 | Z21: 3.76 | AB21: COST | AC21: =LN((F21+R21)/E21) -> 0.27401025 | AD21: =LN((G21+S21)/F21) -> 0.11831671 | AE21: =LN((H21+T21)/G21) -> 0.37186299 | AF21: =LN((I21+U21)/H21) -> 0.21461306 | AG21: =LN((J21+V21)/I21) -> 0.37391829 | AH21: =LN((K21+W21)/J21) -> 0.025568673 | AI21: =LN((L21+X21)/K21) -> 0.3643055 | AJ21: =LN((M21+Y21)/L21) -> 0.35411293 | AK21: =LN((N21+(Y21*(1+Z42)))/M21) -> -0.025405629 | AL21: =AVERAGE(AC21:AK21) -> 0.23014475 | AM21: =AVERAGE(AC21:AJ21) -> 0.26208855 | BJ21: 5 | BK21: 42885 | BL21: 0.204457 | BM21: =LN(BL21/BL20) -> 0 | BN21: =IF(BM21=0, "No Growth", "Growth") -> No Growth | BO21: =IF(BM21=0,1,2) -> 1 | BR21: Q220 | BS21: 0.0014296055 | CH21: 3 | CI21: Q319 | CJ21: 43783 | CK21: 2.1 | CL21: =LN(CK21/CK20) -> 0 | CM21: =IF(CL21<=0, "No Growth", "Growth") -> No Growth
C22: #VALUE! | D22: V | E22: 77.85 | F22: 117.76 | G22: 128.84 | H22: 191.09 | I22: 186.74 | J22: 219.89 | K22: 225.51 | L22: 269.81 | M22: 340.06 | N22: {=_FV(C22,"Price")} -> 341.59 | P22: V | Q22: 0.585 | R22: 0.69 | S22: 0.88 | T22: 1.05 | U22: 1.22 | V22: 1.335 | W22: 1.575 | X22: 1.87 | Y22: 2.15 | Z22: 1.77 | AB22: V | AC22: =LN((F22+R22)/E22) -> 0.41970703 | AD22: =LN((G22+S22)/F22) -> 0.096729626 | AE22: =LN((H22+T22)/G22) -> 0.39965295 | AF22: =LN((I22+U22)/H22) -> -0.016515347 | AG22: =LN((J22+V22)/I22) -> 0.16946301 | AH22: =LN((K22+W22)/J22) -> 0.032196975 | AI22: =LN((L22+X22)/K22) -> 0.1862604 | AJ22: =LN((M22+Y22)/L22) -> 0.23770658 | AK22: =LN((N22+(Y22*(1+Z43)))/M22) -> 0.011705917 | AL22: =AVERAGE(AC22:AK22) -> 0.17076746 | AM22: =AVERAGE(AC22:AJ22) -> 0.19065015 | BJ22: 6 | BK22: 42915 | BL22: 0.205426 | BM22: =LN(BL22/BL21) -> 0.0047281873 | BN22: =IF(BM22=0, "No Growth", "Growth") -> Growth | BO22: =IF(BM22=0,1,2) -> 2 | BR22: Q320 | BS22: 0.0028530942 | CH22: 4 | CI22: Q419 | CJ22: 43874 | CK22: 2.1 | CL22: =LN(CK22/CK21) -> 0 | CM22: =IF(CL22<=0, "No Growth", "Growth") -> No Growth
C23: #VALUE! | D23: SO | E23: 34.24 | F23: 32.74 | G23: 37.17 | H23: 56.3 | I23: 49.17 | J23: 60.43 | K23: 61.18 | L23: 65.42 | M23: 81.9 | N23: {=_FV(C23,"Price")} -> 96.75 | P23: SO | Q23: 2.223 | R23: 2.3 | S23: 2.38 | T23: 2.46 | U23: 2.54 | V23: 2.62 | W23: 2.7 | X23: 2.78 | Y23: 2.86 | Z23: 2.2 | AB23: SO | AC23: =LN((F23+R23)/E23) -> 0.023095715 | AD23: =LN((G23+S23)/F23) -> 0.18896812 | AE23: =LN((H23+T23)/G23) -> 0.45795937 | AF23: =LN((I23+U23)/H23) -> -0.085043349 | AG23: =LN((J23+V23)/I23) -> 0.24864438 | AH23: =LN((K23+W23)/J23) -> 0.055520653 | AI23: =LN((L23+X23)/K23) -> 0.10862423 | AJ23: =LN((M23+Y23)/L23) -> 0.25899571 | AK23: =LN((N23+(Y23*(1+Z44)))/M23) -> 0.19665352 | AL23: =AVERAGE(AC23:AK23) -> 0.16149093 | AM23: =AVERAGE(AC23:AJ23) -> 0.1570956 | BJ23: 7 | BK23: 42944 | BL23: 0.205426 | BM23: =LN(BL23/BL22) -> 0 | BN23: =IF(BM23=0, "No Growth", "Growth") -> No Growth | BO23: =IF(BM23=0,1,2) -> 1 | BR23: Q420 | BS23: 0.0014235003 | CH23: 1 | CI23: Q120 | CJ23: 44021 | CK23: 1.3 | CL23: =LN(CK23/CK22) -> -0.47957308 | CM23: =IF(CL23<=0, "No Growth", "Growth") -> No Growth
C24: #VALUE! | D24: DUK | E24: 54.79 | F24: 57.09 | G24: 66.83 | H24: 77.56 | I24: 77.94 | J24: 90.57 | K24: 91.78 | L24: 89.63 | M24: 109.02 | N24: {=_FV(C24,"Price")} -> 128.31 | P24: DUK | Q24: 3.36 | R24: 3.49 | S24: 3.636 | T24: 3.746 | U24: 3.82 | V24: 3.9 | W24: 3.98 | X24: 4.06 | Y24: 4.14 | Z24: =1.045*3 -> 3.135 | AB24: DUK | AC24: =LN((F24+R24)/E24) -> 0.10045711 | AD24: =LN((G24+S24)/F24) -> 0.21050135 | AE24: =LN((H24+T24)/G24) -> 0.19606773 | AF24: =LN((I24+U24)/H24) -> 0.052736296 | AG24: =LN((J24+V24)/I24) -> 0.19234302 | AH24: =LN((K24+W24)/J24) -> 0.055722029 | AI24: =LN((L24+X24)/K24) -> 0.020597051 | AJ24: =LN((M24+Y24)/L24) -> 0.23311266 | AK24: =LN((N24+(Y24*(1+Z45)))/M24) -> 0.19547871 | AL24: =AVERAGE(AC24:AK24) -> 0.13966844 | AM24: =AVERAGE(AC24:AJ24) -> 0.13269216 | BJ24: 8 | BK24: 42977 | BL24: 0.205426 | BM24: =LN(BL24/BL23) -> 0 | BN24: =IF(BM24=0, "No Growth", "Growth") -> No Growth | BO24: =IF(BM24=0,1,2) -> 1 | BR24: Q121 | BS24: 0.002840936 | CH24: 2 | CI24: Q220 | CJ24: 44112 | CK24: 1.3 | CL24: =LN(CK24/CK23) -> 0 | CM24: =IF(CL24<=0, "No Growth", "Growth") -> No Growth
F25: 2017 | G25: =F25+1 -> 2018 | H25: =G25+1 -> 2019 | I25: =H25+1 -> 2020 | J25: =I25+1 -> 2021 | K25: =J25+1 -> 2022 | L25: =K25+1 -> 2023 | M25: =L25+1 -> 2024 | N25: =M25+1 -> 2025 | R25: 2017 | S25: =R25+1 -> 2018 | T25: =S25+1 -> 2019 | U25: =T25+1 -> 2020 | V25: =U25+1 -> 2021 | W25: =V25+1 -> 2022 | X25: =W25+1 -> 2023 | Y25: =X25+1 -> 2024 | Z25: 2025, e | BJ25: 9 | BK25: 43007 | BL25: 0.205426 | BM25: =LN(BL25/BL24) -> 0 | BN25: =IF(BM25=0, "No Growth", "Growth") -> No Growth | BO25: =IF(BM25=0,1,2) -> 1 | BR25: Q221 | BS25: 0.0014174471 | CH25: 3 | CI25: Q320 | CJ25: 44188 | CK25: 1.3 | CL25: =LN(CK25/CK24) -> 0 | CM25: =IF(CL25<=0, "No Growth", "Growth") -> No Growth
E26: VOO | F26: =LN(F5/E5) -> 0.23367251 | G26: =LN(G5/F5) -> -0.024173443 | H26: =LN(H5/G5) -> 0.19622434 | I26: =LN(I5/H5) -> 0.15837428 | J26: =LN(J5/I5) -> 0.20948389 | K26: =LN(K5/J5) -> -0.08576301 | L26: =LN(L5/K5) -> 0.18862769 | M26: =LN(M5/L5) -> 0.23359661 | N26: =LN(N5/M5) -> 0.21693991 | O26: =AVERAGE(F26:N26) -> 0.14744253 | Q26: VOO | R26: =LN(R5/Q5) -> 0.054092659 | S26: =LN(S5/R5) -> 0.081098785 | T26: =LN(T5/S5) -> 0.16217055 | U26: =LN(U5/T5) -> -0.049301873 | V26: =LN(V5/U5) -> 0.02495474 | W26: =LN(W5/V5) -> 0.089659453 | X26: =LN(X5/W5) -> 0.066669677 | Y26: =LN(Y5/X5) -> 0.053296949 | Z26: =LN(Y5*(1+AVERAGE(R26:Y26))/Y5) -> 0.058580291 | BJ26: 10 | BK26: 43039 | BL26: 0.205426 | BM26: =LN(BL26/BL25) -> 0 | BN26: =IF(BM26=0, "No Growth", "Growth") -> No Growth | BO26: =IF(BM26=0,1,2) -> 1 | BR26: Q321 | BS26: 0.002828881 | CH26: 4 | CI26: Q420 | CJ26: 44294 | CK26: 1.3 | CL26: =LN(CK26/CK25) -> 0 | CM26: =IF(CL26<=0, "No Growth", "Growth") -> No Growth
E27: DIA | F27: =LN(F6/E6) -> 0.29847753 | G27: =LN(G6/F6) -> -0.023375002 | H27: =LN(H6/G6) -> 0.14386464 | I27: =LN(I6/H6) -> 0.081287172 | J27: =LN(J6/I6) -> 0.17467288 | K27: =LN(K6/J6) -> -0.01020589 | L27: =LN(L6/K6) -> 0.13217119 | M27: =LN(M6/L6) -> 0.1720619 | N27: =LN(N6/M6) -> 0.17022352 | O27: =AVERAGE(F27:N27) -> 0.12657533 | Q27: DIA | R27: =LN(R6/Q6) -> 0.088747148 | S27: =LN(S6/R6) -> 0.068760366 | T27: =LN(T6/S6) -> 0.13101482 | U27: =LN(U6/T6) -> -0.038528865 | V27: =LN(V6/U6) -> 0.002441152 | W27: =LN(W6/V6) -> 0.09780856 | X27: =LN(X6/W6) -> 0.071894533 | Y27: =LN(Y6/X6) -> 0.0039604012 | Z27: =LN(Y6*(1+AVERAGE(R27:Y27))/Y6) -> 0.051892267 | BJ27: 11 | BK27: 43069 | BL27: 0.205426 | BM27: =LN(BL27/BL26) -> 0 | BN27: =IF(BM27=0, "No Growth", "Growth") -> No Growth | BO27: =IF(BM27=0,1,2) -> 1 | BR27: Q421 | BS27: 0.050639918 | CH27: 1 | CI27: Q121 | CJ27: 44378 | CK27: 1.4 | CL27: =LN(CK27/CK26) -> 0.074107972 | CM27: =IF(CL27<=0, "No Growth", "Growth") -> Growth
E28: TSLA | F28: =LN(F7/E7) -> 0.34071492 | G28: =LN(G7/F7) -> -0.14313341 | H28: =LN(H7/G7) -> 0.75080756 | I28: =LN(I7/H7) -> 1.8081111 | J28: =LN(J7/I7) -> 0.16589307 | K28: =LN(K7/J7) -> -0.58920966 | L28: =LN(L7/K7) -> 0.078095755 | M28: =LN(M7/L7) -> 0.77024071 | N28: =LN(N7/M7) -> 0.017736 | O28: =AVERAGE(F28:N28) -> 0.35547289 | Q28: TSLA | BJ28: 12 | BK28: 43098 | BL28: 0.206395 | BM28: =LN(BL28/BL27) -> 0.0047059367 | BN28: =IF(BM28=0, "No Growth", "Growth") -> Growth | BO28: =IF(BM28=0,1,2) -> 2 | BR28: Q122 | BS28: 0.026416027 | CH28: 2 | CI28: Q221 | CJ28: 44447 | CK28: 1.5 | CL28: =LN(CK28/CK27) -> 0.068992871 | CM28: =IF(CL28<=0, "No Growth", "Growth") -> Growth
E29: BAC | F29: =LN(F8/E8) -> 0.36178042 | G29: =LN(G8/F8) -> -0.098504771 | H29: =LN(H8/G8) -> 0.16491771 | I29: =LN(I8/H8) -> -0.07545936 | J29: =LN(J8/I8) -> 0.46130441 | K29: =LN(K8/J8) -> -0.23944908 | L29: =LN(L8/K8) -> -0.011899454 | M29: =LN(M8/L8) -> 0.33379392 | N29: =LN(N8/M8) -> 0.24079299 | O29: =AVERAGE(F29:N29) -> 0.12636409 | Q29: BAC | R29: =LN(R8/Q8) -> 0.44468582 | S29: =LN(S8/R8) -> 0.3254224 | T29: =LN(T8/S8) -> 0.2006707 | U29: =LN(U8/T8) -> 0.087011377 | V29: =LN(V8/U8) -> 0.080042708 | W29: =LN(W8/V8) -> 0.09763847 | X29: =LN(X8/W8) -> 0.067441281 | Y29: =LN(Y8/X8) -> 0.083381609 | Z29: =LN(Y8*(1+AVERAGE(R29:Y29))/Y8) -> 0.15980904 | BJ29: 1 | BK29: 43131 | BL29: 0.212209 | BM29: =LN(BL29/BL28) -> 0.02777983 | BN29: =IF(BM29=0, "No Growth", "Growth") -> Growth | BO29: =IF(BM29=0,1,2) -> 2 | BR29: Q222 | BS29: 0.0013486179 | CH29: 3 | CI29: Q321 | CJ29: 44539 | CK29: 1.65 | CL29: =LN(CK29/CK28) -> 0.09531018 | CM29: =IF(CL29<=0, "No Growth", "Growth") -> Growth | CR29: 8 yr Time Frame
E30: SBUX | F30: =LN(F9/E9) -> 0.046856953 | G30: =LN(G9/F9) -> 0.20474817 | H30: =LN(H9/G9) -> 0.23761948 | I30: =LN(I9/H9) -> 0.15258337 | J30: =LN(J9/I9) -> 0.031852704 | K30: =LN(K9/J9) -> 0.12787339 | L30: =LN(L9/K9) -> -0.13894052 | M30: =LN(M9/L9) -> 0.17194491 | N30: =LN(N9/M9) -> -0.015164088 | O30: =AVERAGE(F30:N30) -> 0.091041598 | Q30: SBUX | R30: =LN(R9/Q9) -> 0.21130909 | S30: =LN(S9/R9) -> 0.22884157 | T30: =LN(T9/S9) -> 0.12114438 | U30: =LN(U9/T9) -> 0.12001767 | V30: =LN(V9/U9) -> 0.090971778 | W30: =LN(W9/V9) -> 0.083381609 | X30: =LN(X9/W9) -> 0.076961041 | Y30: =LN(Y9/X9) -> 0.071458964 | Z30: =LN(Y9*(1+AVERAGE(R30:Y30))/Y9) -> 0.11823695 | BJ30: 2 | BK30: 43159 | BL30: 0.212209 | BM30: =LN(BL30/BL29) -> 0 | BN30: =IF(BM30=0, "No Growth", "Growth") -> No Growth | BO30: =IF(BM30=0,1,2) -> 1 | BR30: Q322 | BS30: 0.0026917917 | CH30: 4 | CI30: Q421 | CJ30: 44629 | CK30: 1.65 | CL30: =LN(CK30/CK29) -> 0 | CM30: =IF(CL30<=0, "No Growth", "Growth") -> No Growth
E31: O | F31: =LN(F10/E10) -> -0.070170959 | G31: =LN(G10/F10) -> 0.30341508 | H31: =LN(H10/G10) -> 0.16995084 | I31: =LN(I10/H10) -> -0.23744995 | J31: =LN(J10/I10) -> 0.23517463 | K31: =LN(K10/J10) -> 0.021495021 | L31: =LN(L10/K10) -> -0.16784952 | M31: =LN(M10/L10) -> 0.055816518 | N31: =LN(N10/M10) -> 0.18979087 | O31: =AVERAGE(F31:N31) -> 0.055574726 | Q31: O | R31: =LN(R10/Q10) -> 0.054200632 | S31: =LN(S10/R10) -> 0.039369314 | T31: =LN(T10/S10) -> 0.029099023 | U31: =LN(U10/T10) -> 0.030413108 | V31: =LN(V10/U10) -> 0.021096807 | W31: =LN(W10/V10) -> 0.068591587 | X31: =LN(X10/W10) -> 0.02983317 | Y31: =LN(Y10/X10) -> 0.023879805 | Z31: =LN(Y10*(1+AVERAGE(R31:Y31))/Y10) -> 0.036390202 | BJ31: 3 | BK31: 43188 | BL31: 0.213178 | BM31: =LN(BL31/BL30) -> 0.0045558594 | BN31: =IF(BM31=0, "No Growth", "Growth") -> Growth | BO31: =IF(BM31=0,1,2) -> 2 | BR31: Q422 | BS31: 0.0013431835 | CH31: 1 | CI31: Q122 | CJ31: 44720 | CK31: 1.7 | CL31: =LN(CK31/CK30) -> 0.029852963 | CM31: =IF(CL31<=0, "No Growth", "Growth") -> Growth | CS31: Total % | CT31: Total events | CU31: Wt
E32: VZ | F32: =LN(F11/E11) -> 0.14546646 | G32: =LN(G11/F11) -> 0.064698491 | H32: =LN(H11/G11) -> 0.1180496 | I32: =LN(I11/H11) -> -0.039381825 | J32: =LN(J11/I11) -> 0.016133325 | K32: =LN(K11/J11) -> -0.19393088 | L32: =LN(L11/K11) -> 0.089485989 | M32: =LN(M11/L11) -> -0.0081081525 | N32: =LN(N11/M11) -> 0.17915055 | O32: =AVERAGE(F32:N32) -> 0.04128484 | Q32: VZ | R32: =LN(R11/Q11) -> 0.022189294 | S32: =LN(S11/R11) -> 0.020865138 | T32: =LN(T11/S11) -> 0.021264091 | U32: =LN(U11/T11) -> 0.02001292 | V32: =LN(V11/U11) -> 0.020412956 | W32: =LN(W11/V11) -> 0.019227589 | X32: =LN(X11/W11) -> 0.019627338 | Y32: =LN(Y11/X11) -> 0.018501566 | Z32: =LN(Y11*(1+AVERAGE(R32:Y32))/Y11) -> 0.020060056 | BJ32: 4 | BK32: 43220 | BL32: 0.213178 | BM32: =LN(BL32/BL31) -> 0 | BN32: =IF(BM32=0, "No Growth", "Growth") -> No Growth | BO32: =IF(BM32=0,1,2) -> 1 | BR32: Q123 | BS32: 0.018617559 | CH32: 2 | CI32: Q222 | CJ32: 44812 | CK32: 1.75 | CL32: =LN(CK32/CK31) -> 0.028987537 | CM32: =IF(CL32<=0, "No Growth", "Growth") -> Growth | CR32: Div, Growth | CS32: =SUMIF(CM7:CM44, "Growth", CL7:CL44) -> 0.77503729 | CT32: =COUNTIF(CM7:CM44, "Growth") -> 21 | CU32: =CT32/CT34 -> 0.55263158
E33: AMZN | F33: =LN(F12/E12) -> 0.5664283 | G33: =LN(G12/F12) -> 0.16951124 | H33: =LN(H12/G12) -> 0.15591116 | I33: =LN(I12/H12) -> 0.46754891 | J33: =LN(J12/I12) -> -0.06934493 | K33: =LN(K12/J12) -> -0.37177418 | L33: =LN(L12/K12) -> 0.40872428 | M33: =LN(M12/L12) -> 0.42621062 | N33: =LN(N12/M12) -> 0.010296855 | O33: =AVERAGE(F33:N33) -> 0.19594581 | Q33: AMZN | BJ33: 5 | BK33: 43251 | BL33: 0.213178 | BM33: =LN(BL33/BL32) -> 0 | BN33: =IF(BM33=0, "No Growth", "Growth") -> No Growth | BO33: =IF(BM33=0,1,2) -> 1 | BR33: Q223 | BS33: 0.0091803923 | CH33: 3 | CI33: Q322 | CJ33: 44903 | CK33: 1.8 | CL33: =LN(CK33/CK32) -> 0.028170877 | CM33: =IF(CL33<=0, "No Growth", "Growth") -> Growth | CR33: Div, No Growth | CS33: =SUMIF(CM7:CM44, "No Growth", CL7:CL44) -> -0.47957308 | CT33: =COUNTIF(CM7:CM44, "No Growth") -> 17 | CU33: =CT33/CT34 -> 0.44736842
E34: GOOGL | F34: =LN(F13/E13) -> 0.36564515 | G34: =LN(G13/F13) -> -0.048866815 | H34: =LN(H13/G13) -> 0.24104707 | I34: =LN(I13/H13) -> 0.24320795 | J34: =LN(J13/I13) -> 0.39267333 | K34: =LN(K13/J13) -> -0.31407281 | L34: =LN(L13/K13) -> 0.34888182 | M34: =LN(M13/L13) -> 0.37949719 | N34: =LN(N13/M13) -> 0.55332992 | O34: =AVERAGE(F34:N34) -> 0.2401492 | Q34: GOOGL | BJ34: 6 | BK34: 43280 | BL34: 0.213178 | BM34: =LN(BL34/BL33) -> 0 | BN34: =IF(BM34=0, "No Growth", "Growth") -> No Growth | BO34: =IF(BM34=0,1,2) -> 1 | BR34: Q323 | BS34: 0.0026075634 | CH34: 4 | CI34: Q422 | CJ34: 44994 | CK34: 1.8 | CL34: =LN(CK34/CK33) -> 0 | CM34: =IF(CL34<=0, "No Growth", "Growth") -> No Growth | CT34: =SUM(CT32:CT33) -> 38
E35: CRM | F35: =LN(F14/E14) -> 0.36461473 | G35: =LN(G14/F14) -> 0.28832505 | H35: =LN(H14/G14) -> 0.18200012 | I35: =LN(I14/H14) -> 0.21288099 | J35: =LN(J14/I14) -> 0.030878903 | K35: =LN(K14/J14) -> -0.32567972 | L35: =LN(L14/K14) -> 0.51488428 | M35: =LN(M14/L14) -> 0.20083736 | N35: =LN(N14/M14) -> -0.76662871 | O35: =AVERAGE(F35:N35) -> 0.078012555 | Q35: CRM | BJ35: 7 | BK35: 43312 | BL35: 0.213178 | BM35: =LN(BL35/BL34) -> 0 | BN35: =IF(BM35=0, "No Growth", "Growth") -> No Growth | BO35: =IF(BM35=0,1,2) -> 1 | BR35: Q423 | BS35: 0.0013012364 | CH35: 1 | CI35: Q123 | CJ35: 45085 | CK35: 1.85 | CL35: =LN(CK35/CK34) -> 0.027398974 | CM35: =IF(CL35<=0, "No Growth", "Growth") -> Growth
E36: CVX | F36: =LN(F15/E15) -> 0.1574061 | G36: =LN(G15/F15) -> -0.051328484 | H36: =LN(H15/G15) -> -0.027953054 | I36: =LN(I15/H15) -> -0.1740088 | J36: =LN(J15/I15) -> 0.48376155 | K36: =LN(K15/J15) -> 0.31687566 | L36: =LN(L15/K15) -> -0.12727974 | M36: =LN(M15/L15) -> 0.054009421 | N36: =LN(N15/M15) -> 0.15552707 | O36: =AVERAGE(F36:N36) -> 0.087445526 | Q36: CVX | R36: =LN(R15/Q15) -> 0.0069686693 | S36: =LN(S15/R15) -> 0.036367644 | T36: =LN(T15/S15) -> 0.060624622 | U36: =LN(U15/T15) -> 0.080688911 | V36: =LN(V15/U15) -> 0.028655256 | W36: =LN(W15/V15) -> 0.067359397 | X36: =LN(X15/W15) -> 0.061452779 | Y36: =LN(Y15/X15) -> 0.076470364 | Z36: =LN(Y15*(1+AVERAGE(S36:Y36))/Y15) -> 0.057138751 | BJ36: 8 | BK36: 43343 | BL36: 0.213178 | BM36: =LN(BL36/BL35) -> 0 | BN36: =IF(BM36=0, "No Growth", "Growth") -> No Growth | BO36: =IF(BM36=0,1,2) -> 1 | BR36: Q124 | BS36: 0.0025974041 | CH36: 2 | CI36: Q223 | CJ36: 45176 | CK36: 1.9 | CL36: =LN(CK36/CK35) -> 0.026668247 | CM36: =IF(CL36<=0, "No Growth", "Growth") -> Growth
E37: AMD | F37: =LN(F16/E16) -> 0.28139426 | G37: =LN(G16/F16) -> 0.5746816 | H37: =LN(H16/G16) -> 0.65515472 | I37: =LN(I16/H16) -> 0.60000486 | J37: =LN(J16/I16) -> 0.28823657 | K37: =LN(K16/J16) -> -0.41890291 | L37: =LN(L16/K16) -> 0.80263092 | M37: =LN(M16/L16) -> -0.36895797 | N37: =LN(N16/M16) -> 1.5374652 | O37: =AVERAGE(F37:N37) -> 0.43907858 | Q37: AMD | BJ37: 9 | BK37: 43371 | BL37: 0.214147 | BM37: =LN(BL37/BL36) -> 0.0045351976 | BN37: =IF(BM37=0, "No Growth", "Growth") -> Growth | BO37: =IF(BM37=0,1,2) -> 2 | BR37: Q224 | BS37: 0.015444322 | CH37: 3 | CI37: Q323 | CJ37: 45267 | CK37: 1.9 | CL37: =LN(CK37/CK36) -> 0 | CM37: =IF(CL37<=0, "No Growth", "Growth") -> No Growth
E38: LULU | F38: =LN(F17/E17) -> 0.14712178 | G38: =LN(G17/F17) -> 0.63653015 | H38: =LN(H17/G17) -> 0.48216636 | I38: =LN(I17/H17) -> 0.31699061 | J38: =LN(J17/I17) -> 0.015337539 | K38: =LN(K17/J17) -> -0.08396538 | L38: =LN(L17/K17) -> 0.39124385 | M38: =LN(M17/L17) -> -0.091351695 | N38: =LN(N17/M17) -> -1.2876099 | O38: =AVERAGE(F38:N38) -> 0.058495927 | Q38: LULU | BJ38: 10 | BK38: 43404 | BL38: 0.214147 | BM38: =LN(BL38/BL37) -> 0 | BN38: =IF(BM38=0, "No Growth", "Growth") -> No Growth | BO38: =IF(BM38=0,1,2) -> 1 | BR38: Q324 | BS38: 0.0089002495 | CH38: 4 | CI38: Q423 | CJ38: 45358 | CK38: 1.95 | CL38: =LN(CK38/CK37) -> 0.025975486 | CM38: =IF(CL38<=0, "No Growth", "Growth") -> Growth
E39: LMT | F39: =LN(F18/E18) -> 0.37040245 | G39: =LN(G18/F18) -> -0.17751286 | H39: =LN(H18/G18) -> 0.41606448 | I39: =LN(I18/H18) -> -0.26004278 | J39: =LN(J18/I18) -> 0.21974122 | K39: =LN(K18/J18) -> 0.2002885 | L39: =LN(L18/K18) -> -0.049120313 | M39: =LN(M18/L18) -> 0.10105151 | N39: =LN(N18/M18) -> 0.10264446 | O39: =AVERAGE(F39:N39) -> 0.10261296 | Q39: LMT | R39: =LN(R18/Q18) -> 0.097054327 | S39: =LN(S18/R18) -> 0.09457874 | T39: =LN(T18/S18) -> 0.093090423 | U39: =LN(U18/T18) -> 0.085157808 | V39: =LN(V18/U18) -> 0.078471615 | W39: =LN(W18/V18) -> 0.072759354 | X39: =LN(X18/W18) -> 0.063715814 | Y39: =LN(Y18/X18) -> 0.048202102 | Z39: =LN(Y18*(1+AVERAGE(R39:Y39))/Y18) -> 0.076154024 | BJ39: 11 | BK39: 43434 | BL39: 0.214147 | BM39: =LN(BL39/BL38) -> 0 | BN39: =IF(BM39=0, "No Growth", "Growth") -> No Growth | BO39: =IF(BM39=0,1,2) -> 1 | BR39: Q424 | BS39: 0.003795071 | CH39: 1 | CI39: Q124 | CJ39: 45450 | CK39: 2 | CL39: =LN(CK39/CK38) -> 0.025317808 | CM39: =IF(CL39<=0, "No Growth", "Growth") -> Growth
E40: UPS | F40: =LN(F19/E19) -> 0.18456703 | G40: =LN(G19/F19) -> -0.15684445 | H40: =LN(H19/G19) -> 0.015330632 | I40: =LN(I19/H19) -> 0.4375458 | J40: =LN(J19/I19) -> 0.28721424 | K40: =LN(K19/J19) -> -0.055192223 | L40: =LN(L19/K19) -> -0.22743324 | M40: =LN(M19/L19) -> -0.16984443 | N40: =LN(N19/M19) -> -0.0070136869 | O40: =AVERAGE(F40:N40) -> 0.034258851 | Q40: UPS | R40: =LN(R19/Q19) -> 0.062131781 | S40: =LN(S19/R19) -> 0.092018899 | T40: =LN(T19/S19) -> 0.053488685 | U40: =LN(U19/T19) -> 0.050772325 | V40: =LN(V19/U19) -> 0.0098522964 | W40: =LN(W19/V19) -> 0.39890771 | X40: =LN(X19/W19) -> 0.063715814 | Y40: =LN(Y19/X19) -> 0.0061538656 | Z40: =LN(Y19*(1+AVERAGE(R40:Y40))/Y19) -> 0.088130075 | BJ40: 12 | BK40: 43465 | BL40: 0.214147 | BM40: =LN(BL40/BL39) -> 0 | BN40: =IF(BM40=0, "No Growth", "Growth") -> No Growth | BO40: =IF(BM40=0,1,2) -> 1 | BR40: Q125 | BS40: 0.0025284464 | CH40: 2 | CI40: Q224 | CJ40: 45544 | CK40: 2.05 | CL40: =LN(CK40/CK39) -> 0.024692613 | CM40: =IF(CL40<=0, "No Growth", "Growth") -> Growth
E41: XOM | F41: =LN(F20/E20) -> 0.077072395 | G41: =LN(G20/F20) -> -0.13439728 | H41: =LN(H20/G20) -> -0.11836852 | I41: =LN(I20/H20) -> -0.24914817 | J41: =LN(J20/I20) -> 0.58679438 | K41: =LN(K20/J20) -> 0.46228362 | L41: =LN(L20/K20) -> -0.087157807 | M41: =LN(M20/L20) -> 0.071883047 | N41: =LN(N20/M20) -> 0.26903895 | O41: =AVERAGE(F41:N41) -> 0.097555623 | Q41: XOM | R41: =LN(R20/Q20) -> 0.026491615 | S41: =LN(S20/R20) -> 0.054067221 | T41: =LN(T20/S20) -> 0.060078124 | U41: =LN(U20/T20) -> 0.014472033 | V41: =LN(V20/U20) -> 0.0028694424 | W41: =LN(W20/V20) -> 0.017045867 | X41: =LN(X20/W20) -> 0.035965149 | Y41: =LN(Y20/X20) -> 0.042559614 | Z41: =LN(Y20*(1+AVERAGE(R41:Y41))/Y20) -> 0.031201756 | BJ41: 1 | BK41: 43496 | BL41: 0.218992 | BM41: =LN(BL41/BL40) -> 0.022372504 | BN41: =IF(BM41=0, "No Growth", "Growth") -> Growth | BO41: =IF(BM41=0,1,2) -> 2 | BR41: Q225 | BS41: 0.013724482 | CH41: 3 | CI41: Q324 | CJ41: 45635 | CK41: 2.1 | CL41: =LN(CK41/CK40) -> 0.024097552 | CM41: =IF(CL41<=0, "No Growth", "Growth") -> Growth
E42: COST | F42: =LN(F21/E21) -> 0.22408772 | G42: =LN(G21/F21) -> 0.10702351 | H42: =LN(H21/G21) -> 0.36289432 | I42: =LN(I21/H21) -> 0.17714229 | J42: =LN(J21/I21) -> 0.36757273 | K42: =LN(K21/J21) -> 0.018489752 | L42: =LN(L21/K21) -> 0.33712921 | M42: =LN(M21/L21) -> 0.34951367 | N42: =LN(N21/M21) -> -0.030675625 | O42: =AVERAGE(F42:N42) -> 0.21257529 | Q42: COST | R42: =LN(R21/Q21) -> 1.6320377 | S42: =LN(S21/R21) -> -1.398661 | T42: =LN(T21/S21) -> 0.13126639 | U42: =LN(U21/T21) -> 1.6212724 | V42: =LN(V21/U21) -> -1.4238537 | W42: =LN(W21/V21) -> 0.12822417 | X42: =LN(X21/W21) -> 1.6924298 | Y42: =LN(Y21/X21) -> -1.4382541 | Z42: =LN(Y21*(1+AVERAGE(R42:Y42))/Y21) -> 0.11159298 | BJ42: 2 | BK42: 43524 | BL42: 0.218992 | BM42: =LN(BL42/BL41) -> 0 | BN42: =IF(BM42=0, "No Growth", "Growth") -> No Growth | BO42: =IF(BM42=0,1,2) -> 1 | BR42: Q325 | BS42: 0 | CH42: 4 | CI42: Q424 | CJ42: 45726 | CK42: 2.1 | CL42: =LN(CK42/CK41) -> 0 | CM42: =IF(CL42<=0, "No Growth", "Growth") -> No Growth
E43: V | F43: =LN(F22/E22) -> 0.41386476 | G43: =LN(G22/F22) -> 0.089922669 | H43: =LN(H22/G22) -> 0.3941732 | I43: =LN(I22/H22) -> -0.023027246 | J43: =LN(J22/I22) -> 0.16341015 | K43: =LN(K22/J22) -> 0.025237083 | L43: =LN(L22/K22) -> 0.1793535 | M43: =LN(M22/L22) -> 0.23140407 | N43: =LN(N22/M22) -> 0.0044891149 | O43: =AVERAGE(F43:N43) -> 0.16431414 | Q43: V | R43: =LN(R22/Q22) -> 0.16507975 | S43: =LN(S22/R22) -> 0.24323031 | T43: =LN(T22/S22) -> 0.17662354 | U43: =LN(U22/T22) -> 0.15006069 | V43: =LN(V22/U22) -> 0.090080433 | W43: =LN(W22/V22) -> 0.16532398 | X43: =LN(X22/W22) -> 0.17168316 | Y43: =LN(Y22/X22) -> 0.13952941 | Z43: =LN(Y22*(1+AVERAGE(R43:Y43))/Y22) -> 0.1507461 | BJ43: 3 | BK43: 43553 | BL43: 0.218992 | BM43: =LN(BL43/BL42) -> 0 | BN43: =IF(BM43=0, "No Growth", "Growth") -> No Growth | BO43: =IF(BM43=0,1,2) -> 1 | CH43: 1 | CI43: Q125 | CJ43: 45817 | CK43: 2.1 | CL43: =LN(CK43/CK42) -> 0 | CM43: =IF(CL43<=0, "No Growth", "Growth") -> No Growth
E44: SO | F44: =LN(F23/E23) -> -0.044796979 | G44: =LN(G23/F23) -> 0.12690441 | H44: =LN(H23/G23) -> 0.41519255 | I44: =LN(I23/H23) -> -0.13541085 | J44: =LN(J23/I23) -> 0.20620199 | K44: =LN(K23/J23) -> 0.012334668 | L44: =LN(L23/K23) -> 0.067007683 | M44: =LN(M23/L23) -> 0.22467097 | N44: =LN(N23/M23) -> 0.16663134 | O44: =AVERAGE(F44:N44) -> 0.11541509 | Q44: SO | R44: =LN(R23/Q23) -> 0.034051488 | S44: =LN(S23/R23) -> 0.034191365 | T44: =LN(T23/S23) -> 0.033060862 | U44: =LN(U23/T23) -> 0.032002731 | V44: =LN(V23/U23) -> 0.031010237 | W44: =LN(W23/V23) -> 0.030077455 | X44: =LN(X23/W23) -> 0.029199155 | Y44: =LN(Y23/X23) -> 0.028370697 | Z44: =LN(Y23*(1+AVERAGE(R44:Y44))/Y23) -> 0.03100969 | BJ44: 4 | BK44: 43585 | BL44: 0.218992 | BM44: =LN(BL44/BL43) -> 0 | BN44: =IF(BM44=0, "No Growth", "Growth") -> No Growth | BO44: =IF(BM44=0,1,2) -> 1 | CH44: 2 | CI44: Q225 | CJ44: 45909 | CK44: 2.15 | CL44: =LN(CK44/CK43) -> 0.023530497 | CM44: =IF(CL44<=0, "No Growth", "Growth") -> Growth
E45: DUK | F45: =LN(F24/E24) -> 0.041121274 | G45: =LN(G24/F24) -> 0.15752311 | H45: =LN(H24/G24) -> 0.14889975 | I45: =LN(I24/H24) -> 0.0048874695 | J45: =LN(J24/I24) -> 0.15018373 | K45: =LN(K24/J24) -> 0.013271377 | L45: =LN(L24/K24) -> -0.023704324 | M45: =LN(M24/L24) -> 0.19584127 | N45: =LN(N24/M24) -> 0.16291786 | O45: =AVERAGE(F45:N45) -> 0.094549057 | Q45: DUK | R45: =LN(R24/Q24) -> 0.037960762 | S45: =LN(S24/R24) -> 0.04098244 | T45: =LN(T24/S24) -> 0.029804428 | U45: =LN(U24/T24) -> 0.019561819 | V45: =LN(V24/U24) -> 0.020726131 | W45: =LN(W24/V24) -> 0.020305266 | X45: =LN(X24/W24) -> 0.019901154 | Y45: =LN(Y24/X24) -> 0.019512814 | Z45: =LN(Y24*(1+AVERAGE(R45:Y45))/Y24) -> 0.025759703 | BJ45: 5 | BK45: 43616 | BL45: 0.218992 | BM45: =LN(BL45/BL44) -> 0 | BN45: =IF(BM45=0, "No Growth", "Growth") -> No Growth | BO45: =IF(BM45=0,1,2) -> 1 | CL45: Mean | CM45: Stdev
BJ46: 6 | BK46: 43644 | BL46: 0.219961 | BM46: =LN(BL46/BL45) -> 0.0044150584 | BN46: =IF(BM46=0, "No Growth", "Growth") -> Growth | BO46: =IF(BM46=0,1,2) -> 2 | CK46: 8 years | CL46: =AVERAGE(CL7:CL44) -> 0.007775374 | CM46: =_xlfn.STDEV.S(CL7:CL44) -> 0.084570776
BJ47: 7 | BK47: 43677 | BL47: 0.219961 | BM47: =LN(BL47/BL46) -> 0 | BN47: =IF(BM47=0, "No Growth", "Growth") -> No Growth | BO47: =IF(BM47=0,1,2) -> 1 | CK47: After Pandemic | CL47: =AVERAGE(CL26:CL44) -> 0.026479136 | CM47: =_xlfn.STDEV.S(CL26:CL44) -> 0.026937256
BJ48: 8 | BK48: 43707 | BL48: 0.219961 | BM48: =LN(BL48/BL47) -> 0 | BN48: =IF(BM48=0, "No Growth", "Growth") -> No Growth | BO48: =IF(BM48=0,1,2) -> 1
BJ49: 9 | BK49: 43738 | BL49: 0.219961 | BM49: =LN(BL49/BL48) -> 0 | BN49: =IF(BM49=0, "No Growth", "Growth") -> No Growth | BO49: =IF(BM49=0,1,2) -> 1
BJ50: 10 | BK50: 43769 | BL50: 0.219961 | BM50: =LN(BL50/BL49) -> 0 | BN50: =IF(BM50=0, "No Growth", "Growth") -> No Growth | BO50: =IF(BM50=0,1,2) -> 1
BJ51: 11 | BK51: 43798 | BL51: 0.219961 | BM51: =LN(BL51/BL50) -> 0 | BN51: =IF(BM51=0, "No Growth", "Growth") -> No Growth | BO51: =IF(BM51=0,1,2) -> 1
BJ52: 12 | BK52: 43830 | BL52: 0.22093 | BM52: =LN(BL52/BL51) -> 0.0043956514 | BN52: =IF(BM52=0, "No Growth", "Growth") -> Growth | BO52: =IF(BM52=0,1,2) -> 2
BJ53: 1 | BK53: 43861 | BL53: 0.225775 | BM53: =LN(BL53/BL52) -> 0.021693019 | BN53: =IF(BM53=0, "No Growth", "Growth") -> Growth | BO53: =IF(BM53=0,1,2) -> 2
BJ54: 2 | BK54: 43889 | BL54: 0.225775 | BM54: =LN(BL54/BL53) -> 0 | BN54: =IF(BM54=0, "No Growth", "Growth") -> No Growth | BO54: =IF(BM54=0,1,2) -> 1
D55: Raw Prices, Adjusted Prices for Jan. 1 of following year of rep | BJ55: 3 | BK55: 43921 | BL55: 0.225775 | BM55: =LN(BL55/BL54) -> 0 | BN55: =IF(BM55=0, "No Growth", "Growth") -> No Growth | BO55: =IF(BM55=0,1,2) -> 1
E56: 2016 | F56: 2017 | G56: =F56+1 -> 2018 | H56: =G56+1 -> 2019 | I56: =H56+1 -> 2020 | J56: =I56+1 -> 2021 | K56: =J56+1 -> 2022 | L56: =K56+1 -> 2023 | M56: =L56+1 -> 2024 | N56: 2025 | P56: μ | BJ56: 4 | BK56: 43951 | BL56: 0.225775 | BM56: =LN(BL56/BL55) -> 0 | BN56: =IF(BM56=0, "No Growth", "Growth") -> No Growth | BO56: =IF(BM56=0,1,2) -> 1
C57: #VALUE! | D57: CROX | E57: 7.3 | F57: 13.51 | G57: 28.72 | H57: 37.91 | I57: 70.02 | J57: 102.62 | K57: 121.77 | L57: 101.48 | M57: 102.07 | N57: {=_FV(C57,"Price")} -> 125.33 | BJ57: 5 | BK57: 43980 | BL57: 0.225775 | BM57: =LN(BL57/BL56) -> 0 | BN57: =IF(BM57=0, "No Growth", "Growth") -> No Growth | BO57: =IF(BM57=0,1,2) -> 1
D58: YoY Stock Growth | F58: =LN(F57/E57) -> 0.6155558 | G58: =LN(G57/F57) -> 0.75416359 | H58: =LN(H57/G57) -> 0.27762119 | I58: =LN(I57/H57) -> 0.61356599 | J58: =LN(J57/I57) -> 0.38225193 | K58: =LN(K57/J57) -> 0.17110117 | L58: =LN(L57/K57) -> -0.18227228 | M58: =LN(M57/L57) -> 0.0057971177 | N58: =LN(N57/M57) -> 0.20529141 | P58: =AVERAGE(F58:N58) -> 0.31589732 | BJ58: 6 | BK58: 44012 | BL58: 0.226744 | BM58: =LN(BL58/BL57) -> 0.0042826996 | BN58: =IF(BM58=0, "No Growth", "Growth") -> Growth | BO58: =IF(BM58=0,1,2) -> 2
BJ59: 7 | BK59: 44043 | BL59: 0.226744 | BM59: =LN(BL59/BL58) -> 0 | BN59: =IF(BM59=0, "No Growth", "Growth") -> No Growth | BO59: =IF(BM59=0,1,2) -> 1
BJ60: 8 | BK60: 44074 | BL60: 0.226744 | BM60: =LN(BL60/BL59) -> 0 | BN60: =IF(BM60=0, "No Growth", "Growth") -> No Growth | BO60: =IF(BM60=0,1,2) -> 1
BJ61: 9 | BK61: 44104 | BL61: 0.226744 | BM61: =LN(BL61/BL60) -> 0 | BN61: =IF(BM61=0, "No Growth", "Growth") -> No Growth | BO61: =IF(BM61=0,1,2) -> 1
BJ62: 10 | BK62: 44134 | BL62: 0.226744 | BM62: =LN(BL62/BL61) -> 0 | BN62: =IF(BM62=0, "No Growth", "Growth") -> No Growth | BO62: =IF(BM62=0,1,2) -> 1
BJ63: 11 | BK63: 44165 | BL63: 0.226744 | BM63: =LN(BL63/BL62) -> 0 | BN63: =IF(BM63=0, "No Growth", "Growth") -> No Growth | BO63: =IF(BM63=0,1,2) -> 1
BJ64: 12 | BK64: 44196 | BL64: 0.227713 | BM64: =LN(BL64/BL63) -> 0.0042644363 | BN64: =IF(BM64=0, "No Growth", "Growth") -> Growth | BO64: =IF(BM64=0,1,2) -> 2
BJ65: 1 | BK65: 44225 | BL65: 0.227713 | BM65: =LN(BL65/BL64) -> 0 | BN65: =IF(BM65=0, "No Growth", "Growth") -> No Growth | BO65: =IF(BM65=0,1,2) -> 1
BJ66: 2 | BK66: 44253 | BL66: 0.227713 | BM66: =LN(BL66/BL65) -> 0 | BN66: =IF(BM66=0, "No Growth", "Growth") -> No Growth | BO66: =IF(BM66=0,1,2) -> 1
BJ67: 3 | BK67: 44286 | BL67: 0.227713 | BM67: =LN(BL67/BL66) -> 0 | BN67: =IF(BM67=0, "No Growth", "Growth") -> No Growth | BO67: =IF(BM67=0,1,2) -> 1
BJ68: 4 | BK68: 44316 | BL68: 0.227713 | BM68: =LN(BL68/BL67) -> 0 | BN68: =IF(BM68=0, "No Growth", "Growth") -> No Growth | BO68: =IF(BM68=0,1,2) -> 1
BJ69: 5 | BK69: 44344 | BL69: 0.227713 | BM69: =LN(BL69/BL68) -> 0 | BN69: =IF(BM69=0, "No Growth", "Growth") -> No Growth | BO69: =IF(BM69=0,1,2) -> 1
BJ70: 6 | BK70: 44377 | BL70: 0.228682 | BM70: =LN(BL70/BL69) -> 0.0042463281 | BN70: =IF(BM70=0, "No Growth", "Growth") -> Growth | BO70: =IF(BM70=0,1,2) -> 2
... BJ75: 11 | BK75: 44530 | BL75: 0.246 | BM75: =LN(BL75/BL74) -> 0.072999144 | BN75: =IF(BM75=0, "No Growth", "Growth") -> Growth | BO75: =IF(BM75=0,1,2) -> 2
BJ76: 12 | BK76: 44561 | BL76: 0.247 | BM76: =LN(BL76/BL75) -> 0.0040568007 | BN76: =IF(BM76=0, "No Growth", "Growth") -> Growth | BO76: =IF(BM76=0,1,2) -> 2 | BQ76: Presence in Patterns
BJ77: 1 | BK77: 44592 | BL77: 0.247 | BM77: =LN(BL77/BL76) -> 0 | BN77: =IF(BM77=0, "No Growth", "Growth") -> No Growth | BO77: =IF(BM77=0,1,2) -> 1 | BQ77: No Growth | BR77: =SUMIF(BN6:BN121, "No Growth", BO6:BO121) -> 88
BJ78: 2 | BK78: 44620 | BL78: 0.247 | BM78: =LN(BL78/BL77) -> 0 | BN78: =IF(BM78=0, "No Growth", "Growth") -> No Growth | BO78: =IF(BM78=0,1,2) -> 1 | BQ78: Growth | BR78: =(SUMIF(BN6:BN121, "Growth", BO6:BO121))/2 -> 28
BJ79: 3 | BK79: 44651 | BL79: 0.247 | BM79: =LN(BL79/BL78) -> 0 | BN79: =IF(BM79=0, "No Growth", "Growth") -> No Growth | BO79: =IF(BM79=0,1,2) -> 1 | BQ79: Total | BR79: =SUM(BR77:BR78) -> 116
BJ80: 4 | BK80: 44680 | BL80: 0.247 | BM80: =LN(BL80/BL79) -> 0 | BN80: =IF(BM80=0, "No Growth", "Growth") -> No Growth | BO80: =IF(BM80=0,1,2) -> 1
BJ81: 5 | BK81: 44712 | BL81: 0.247 | BM81: =LN(BL81/BL80) -> 0 | BN81: =IF(BM81=0, "No Growth", "Growth") -> No Growth | BO81: =IF(BM81=0,1,2) -> 1
BJ82: 6 | BK82: 44742 | BL82: 0.248 | BM82: =LN(BL82/BL81) -> 0.0040404095 | BN82: =IF(BM82=0, "No Growth", "Growth") -> Growth | BO82: =IF(BM82=0,1,2) -> 2
BJ83: 7 | BK83: 44771 | BL83: 0.248 | BM83: =LN(BL83/BL82) -> 0 | BN83: =IF(BM83=0, "No Growth", "Growth") -> No Growth | BO83: =IF(BM83=0,1,2) -> 1
BJ84: 8 | BK84: 44804 | BL84: 0.248 | BM84: =LN(BL84/BL83) -> 0 | BN84: =IF(BM84=0, "No Growth", "Growth") -> No Growth | BO84: =IF(BM84=0,1,2) -> 1
BJ85: 9 | BK85: 44834 | BL85: 0.248 | BM85: =LN(BL85/BL84) -> 0 | BN85: =IF(BM85=0, "No Growth", "Growth") -> No Growth | BO85: =IF(BM85=0,1,2) -> 1
BJ86: 10 | BK86: 44865 | BL86: 0.248 | BM86: =LN(BL86/BL85) -> 0 | BN86: =IF(BM86=0, "No Growth", "Growth") -> No Growth | BO86: =IF(BM86=0,1,2) -> 1
BJ87: 11 | BK87: 44895 | BL87: 0.248 | BM87: =LN(BL87/BL86) -> 0 | BN87: =IF(BM87=0, "No Growth", "Growth") -> No Growth | BO87: =IF(BM87=0,1,2) -> 1
BJ88: 12 | BK88: 44925 | BL88: 0.249 | BM88: =LN(BL88/BL87) -> 0.0040241503 | BN88: =IF(BM88=0, "No Growth", "Growth") -> Growth | BO88: =IF(BM88=0,1,2) -> 2
BJ89: 1 | BK89: 44957 | BL89: 0.249 | BM89: =LN(BL89/BL88) -> 0 | BN89: =IF(BM89=0, "No Growth", "Growth") -> No Growth | BO89: =IF(BM89=0,1,2) -> 1
BJ90: 2 | BK90: 44985 | BL90: 0.255 | BM90: =LN(BL90/BL89) -> 0.023810649 | BN90: =IF(BM90=0, "No Growth", "Growth") -> Growth | BO90: =IF(BM90=0,1,2) -> 2
BJ91: 3 | BK91: 45016 | BL91: 0.255 | BM91: =LN(BL91/BL90) -> 0 | BN91: =IF(BM91=0, "No Growth", "Growth") -> No Growth | BO91: =IF(BM91=0,1,2) -> 1
... BJ121: 9 | BK121: 45931 | BL121: 0.27 | BM121: =LN(BL121/BL120) -> 0.0037105794 | BN121: =IF(BM121=0, "No Growth", "Growth") -> Growth | BO121: =IF(BM121=0,1,2) -> 2
BJ122: 10
BJ123: 11
BJ124: 12 | BM124: G | BN124: =COUNTIF(BN6:BN121, "Growth") -> 28
BM125: NG | BN125: =COUNTIF(BN6:BN121, "No Growth") -> 88
BL129: Total % | BM129: Total Events, <0% | BN129: Total Events, >=0% | BO129: Total Events | BP129: % chance of increase | BQ129: % change of decrease | BR129: Mean increase of Event
BK130: Jan | BL130: =SUMIF(BJ6:BJ121, "1", BM6:BM121) -> 0.11049789 | BM130: =COUNTIFS($BJ$6:$BJ$121, "1", $BN$6:$BN$121, "Growth") -> 4 | BN130: =COUNTIFS($BJ$6:$BJ$121, "1", $BN$6:$BN$121, "No Growth") -> 5 | BO130: =SUM(BM130:BN130) -> 9 | BP130: =BM130/$BO130 -> 0.44444444 | BQ130: =BN130/$BO130 -> 0.55555556 | BR130: =BL130/BM130 -> 0.027624473
BK131: Feb | BL131: =SUMIF(BJ6:BJ121, "2", BM6:BM121) -> 0.038848526 | BM131: =COUNTIFS(BJ6:BJ121, "2", BN6:BN121, "Growth") -> 2 | BN131: =COUNTIFS($BJ$6:$BJ$121, "2", $BN$6:$BN$121, "No Growth") -> 8 | BO131: =SUM(BM131:BN131) -> 10 | BP131: =BM131/$BO131 -> 0.2 | BQ131: =BN131/$BO131 -> 0.8 | BR131: =BL131/BM131 -> 0.019424263
BK132: Mar | BL132: =SUMIF(BJ6:BJ121, "3", BM6:BM121) -> 0.0082802585 | BM132: =COUNTIFS(BJ6:BJ121, "3", BN6:BN121, "Growth") -> 2 | BN132: =COUNTIFS($BJ$6:$BJ$121, "3", $BN$6:$BN$121, "No Growth") -> 8 | BO132: =SUM(BM132:BN132) -> 10 | BP132: =BM132/$BO132 -> 0.2 | BQ132: =BN132/$BO132 -> 0.8 | BR132: =BL132/BM132 -> 0.0041401292
BK133: Apr | BL133: =SUMIF(BJ6:BJ121, "4", BM6:BM121) -> 0 | BM133: =COUNTIFS(BJ6:BJ121, "4", BN6:BN121, "Growth") -> 0 | BN133: =COUNTIFS($BJ$6:$BJ$121, "4", $BN$6:$BN$121, "No Growth") -> 10 | BO133: =SUM(BM133:BN133) -> 10 | BP133: =BM133/$BO133 -> 0 | BQ133: =BN133/$BO133 -> 1 | BR133: 0
BK134: May | BL134: =SUMIF(BJ6:BJ121, "5", BM6:BM121) -> 0.023077947 | BM134: =COUNTIFS(BJ6:BJ121, "5", BN6:BN121, "Growth") -> 1 | BN134: =COUNTIFS($BJ$6:$BJ$121, "5", $BN$6:$BN$121, "No Growth") -> 9 | BO134: =SUM(BM134:BN134) -> 10 | BP134: =BM134/$BO134 -> 0.1 | BQ134: =BN134/$BO134 -> 0.9 | BR134: =BL134/BM134 -> 0.023077947
BK135: Jun | BL135: =SUMIF(BJ6:BJ121, "6", BM6:BM121) -> 0.030639176 | BM135: =COUNTIFS(BJ6:BJ121, "6", BN6:BN121, "Growth") -> 7 | BN135: =COUNTIFS($BJ$6:$BJ$121, "6", $BN$6:$BN$121, "No Growth") -> 3 | BO135: =SUM(BM135:BN135) -> 10 | BP135: =BM135/$BO135 -> 0.7 | BQ135: =BN135/$BO135 -> 0.3 | BR135: =BL135/BM135 -> 0.0043770252
BK136: Jul | BL136: =SUMIF(BJ6:BJ121, "7", BM6:BM121) -> 0 | BM136: =COUNTIFS(BJ6:BJ121, "7", BN6:BN121, "Growth") -> 0 | BN136: =COUNTIFS($BJ$6:$BJ$121, "7", $BN$6:$BN$121, "No Growth") -> 10 | BO136: =SUM(BM136:BN136) -> 10 | BP136: =BM136/$BO136 -> 0 | BQ136: =BN136/$BO136 -> 1 | BR136: 0
BK137: Aug | BL137: =SUMIF(BJ6:BJ121, "8", BM6:BM121) -> 0.009950433 | BM137: =COUNTIFS(BJ6:BJ121, "8", BN6:BN121, "Growth") -> 1 | BN137: =COUNTIFS($BJ$6:$BJ$121, "8", $BN$6:$BN$121, "No Growth") -> 9 | BO137: =SUM(BM137:BN137) -> 10 | BP137: =BM137/$BO137 -> 0.1 | BQ137: =BN137/$BO137 -> 0.9 | BR137: =BL137/BM137 -> 0.009950433
...

Sheet Notes
B4: Key Takeaways
B6: Constraints = Min σP , μP >= 18.5% , βP >= 1.055 , Sector <= 20% , Security >= 3.25%
B7: In order to achieve a 18.5% return on the portfolio, while reducing σP to the smallest it could, Solver is saying to double down on BAC and CRM and significantly
B8: increase XOM to 16.75% of the TotalP. Furthermore, to meet the βP >= 1.055 constraint, while maintaining <= 20% on a sector, it says to max out Technology,
B9: Consumer Cyclical, Financial Services, and Energy.
C11: + reduce VOO, TSLA, O, VZ, SBUX, DIA, GOOGL, CVX, and LULU
C12: + increase BAC, AMZN, CRM, AMD, LMT, UPS, and XOM
C13: + results: σP = 11.96% | μP = 18.5% | βP = 1.055
B16: The P is poorly constructed, with a lot of losers (O, CVX, UPS, and SBUX), which is the reason why the P's average return for the past 8-years has been 25.66%
B17: with a HIGH standard deviation of 28.48%.
B19: The P should be introduced with two or more solid winners that can take from the HIGH sector % of the total P of Consumer Cyclical.
B21: Solver requests to significantly increase the WTs of XOM, CVX, and V to minimize the standard deviation of the overall portfolio. Not to
B22: mention, that it also requests to decrease the positions: SBUX, AMZN, TSLA, to make room for the increases in the previously mentioned
B23: securities. However, one key observation that continues to show up in every computation (excl. a constraint to keep the WT @ C) is
B24: Realty Income's (O) total position ratio -- seeing as too risky due to large deviations and poor returns.
